Workbook
Name Barcode: 'Master (Filled)'!$Q$27:$R$30
Name Category: 'Master (Filled)'!$Q$14:$R$18
Name Data_Table: 'Data Table Analysis'!$A$5:$B$9
Name Harga: 'Master (Filled)'!$Y$7:$Z$37
Name Harga_Rata_Rata: 'Master (Filled)'!$U$26:$V$29
Name Harga1: 'Master (Filled)'!#REF!
Name Point: 'Master (Filled)'!$Q$34:$V$35
Name Produk: 'Master (Filled)'!$T$7:$W$22
Name ProdukID: 'Master (Filled)'!$Q$7:$Q$10
Name Slicer_Category: #N/A
Name Slicer_Domicile: #N/A
Name Slicer_Gender: #N/A

Sheet Master (Blank)
B3: Supermarket Family Database 2023
A4: No | B4: Input Date | C4: Customer Name | D4: Gender | E4: Domicile | F4: Member Code | G4: Product ID | H4: Category | I4: Name of Product | J4: Barcode | K4: Quantity | L4: Price item | M4: Tax | N4: Member Point | O4: Total Payment
A5: 1 | B5: 44959 | C5: Sean Laura Edelyn | D5: F | E5: Jakarta | F5: P1114 | G5: PB103 | I5: Cake & bread | K5: 5
A6: 2 | B6: 44959 | C6: Jennifer Savira | D6: F | E6: Bogor | F6: P1214 | G6: PB101 | I6: Chilled & frozen product | K6: 8
A7: 3 | B7: 44959 | C7: Raissa Zeviw | D7: F | E7: Bandung | F7: P1414 | G7: PB103 | I7: Cake & bread | K7: 8
A8: 4 | B8: 44959 | C8: Nadia Sarah Jayadi | D8: F | E8: Bogor | F8: G1111 | G8: PB102 | I8: Eggs | K8: 2
A9: 5 | B9: 44959 | C9: Michael Harvey Tan | D9: M | E9: Jakarta | F9: G1412 | G9: NF104 | I9: Baby need | K9: 2
A10: 6 | B10: 44959 | C10: Andreas Wijaya Lukita | D10: M | E10: Jakarta | F10: G1411 | G10: NF101 | I10: Personal care | K10: 2
A11: 7 | B11: 44959 | C11: Widya Michael Sofiany | D11: F | E11: Jakarta | F11: G1413 | G11: NF101 | I11: Personal care | K11: 3
A12: 8 | B12: 44960 | C12: Selena Swift Widodo | D12: F | E12: Jakarta | F12: S1113 | G12: NF102 | I12: Baby need | K12: 4
A13: 9 | B13: 44960 | C13: Putri Selena Utama | D13: F | E13: Tangerang | F13: S1111 | G13: NF104 | I13: Baby need | K13: 4
A14: 10 | B14: 44960 | C14: Harry Anderson | D14: M | E14: Bogor | F14: S1314 | G14: FP101 | I14: Instant Noodle & Food | K14: 2
A15: 11 | B15: 44960 | C15: Jimmy Michael Peter | D15: M | E15: Bogor | F15: S1611 | G15: FP102 | I15: Instant Noodle & Food | K15: 3
A16: 12 | B16: 44960 | C16: Sammy Hutagalung | D16: M | E16: Tangerang | F16: S1512 | G16: FP104 | I16: Instant Noodle & Food | K16: 2
... A184: 180 | B184: 44990 | C184: Milaney Wangsa Widyatama | D184: F | E184: Bekasi | F184: S1113 | G184: NF104 | I184: Personal care | K184: 8
J185: Total Quantity | K185: =SUM(K5:K184) -> 1100 | N185: Total Payment
N186: Rata-rata Total Payment

Sheet Master (Filled)
G1: Supermarket Family Database 2023
A3: No | B3: Input Date | C3: Customer Name | D3: Gender | E3: Domicile | F3: Member Code | G3: Product ID | H3: Category | I3: Name of Product | J3: Barcode | K3: Quantity | L3: Price item | M3: Tax | N3: Member Point | O3: Total Payment
A4: 1 | B4: 44959 | C4: Sean Laura Edelyn | D4: F | E4: Jakarta | F4: P1114 | G4: PB103 | H4: =VLOOKUP(LEFT(G4,2),Category,2,0) -> Perishable | I4: Cake & bread | J4: =VLOOKUP(LEFT(F4,1),Barcode,2,0) -> Platinum | K4: 5 | L4: =INDEX($Z$8:$Z$37,MATCH(I4,$Y$8:$Y$37,0)) -> 49999 | M4: =IF(K4>8,3%,2%) -> 0.02 | N4: =HLOOKUP(VALUE(RIGHT(F4,2)),Point,2,0) -> 20 Point | O4: =(K4*L4)-(L4*M4) -> 248995.02
A5: 2 | B5: 44959 | C5: Jennifer Savira | D5: F | E5: Bogor | F5: P1214 | G5: PB101 | H5: =VLOOKUP(LEFT(G5,2),Category,2,0) -> Perishable | I5: Chilled & frozen product | J5: =VLOOKUP(LEFT(F5,1),Barcode,2,0) -> Platinum | K5: 8 | L5: =INDEX($Z$8:$Z$37,MATCH(I5,$Y$8:$Y$37,0)) -> 69999 | M5: =IF(K5>8,3%,2%) -> 0.02 | N5: =HLOOKUP(VALUE(RIGHT(F5,2)),Point,2,0) -> 20 Point | O5: =(K5*L5)-(L5*M5) -> 558592.02 | Q5: Yang termasuk Product ID | T5: Tabel Produk Berdasarkan Category | Y5: Tabel Harga Berdasarkan Nama Produk
A6: 3 | B6: 44959 | C6: Raissa Zeviw | D6: F | E6: Bandung | F6: P1414 | G6: PB103 | H6: =VLOOKUP(LEFT(G6,2),Category,2,0) -> Perishable | I6: Cake & bread | J6: =VLOOKUP(LEFT(F6,1),Barcode,2,0) -> Platinum | K6: 8 | L6: =INDEX($Z$8:$Z$37,MATCH(I6,$Y$8:$Y$37,0)) -> 49999 | M6: =IF(K6>8,3%,2%) -> 0.02 | N6: =HLOOKUP(VALUE(RIGHT(F6,2)),Point,2,0) -> 20 Point | O6: =(K6*L6)-(L6*M6) -> 398992.02
A7: 4 | B7: 44959 | C7: Nadia Sarah Jayadi | D7: F | E7: Bogor | F7: G1111 | G7: PB102 | H7: =VLOOKUP(LEFT(G7,2),Category,2,0) -> Perishable | I7: Eggs | J7: =VLOOKUP(LEFT(F7,1),Barcode,2,0) -> Gold | K7: 2 | L7: =INDEX($Z$8:$Z$37,MATCH(I7,$Y$8:$Y$37,0)) -> 25500 | M7: =IF(K7>8,3%,2%) -> 0.02 | N7: =HLOOKUP(VALUE(RIGHT(F7,2)),Point,2,0) -> 5 Point | O7: =(K7*L7)-(L7*M7) -> 50490 | Q7: Product ID | T7: Food Product | U7: Non Food Product | V7: General Merchandise Product | W7: Perishable | Y7: Nama Produk | Z7: Price/Unit
A8: 5 | B8: 44959 | C8: Michael Harvey Tan | D8: M | E8: Jakarta | F8: G1412 | G8: NF104 | H8: =VLOOKUP(LEFT(G8,2),Category,2,0) -> Non Food Product | I8: Baby need | J8: =VLOOKUP(LEFT(F8,1),Barcode,2,0) -> Gold | K8: 2 | L8: =INDEX($Z$8:$Z$37,MATCH(I8,$Y$8:$Y$37,0)) -> 195000 | M8: =IF(K8>8,3%,2%) -> 0.02 | N8: =HLOOKUP(VALUE(RIGHT(F8,2)),Point,2,0) -> 10 Point | O8: =(K8*L8)-(L8*M8) -> 386100 | Q8: Name of Product | T8: Beverage | U8: Personal care | V8: Battery, film, electrical & lamp | W8: Eggs | Y8: Beverage | Z8: 75000
A9: 6 | B9: 44959 | C9: Andreas Wijaya Lukita | D9: M | E9: Jakarta | F9: G1411 | G9: NF101 | H9: =VLOOKUP(LEFT(G9,2),Category,2,0) -> Non Food Product | I9: Personal care | J9: =VLOOKUP(LEFT(F9,1),Barcode,2,0) -> Gold | K9: 2 | L9: =INDEX($Z$8:$Z$37,MATCH(I9,$Y$8:$Y$37,0)) -> 85500 | M9: =IF(K9>8,3%,2%) -> 0.02 | N9: =HLOOKUP(VALUE(RIGHT(F9,2)),Point,2,0) -> 5 Point | O9: =(K9*L9)-(L9*M9) -> 169290 | Q9: Product Brand | T9: Tea, coffee and creamer | U9: Oral hygiene | V9: Apparel, towel and underwear | W9: Cake & bread | Y9: Tea, coffee and creamer | Z9: 120000
A10: 7 | B10: 44959 | C10: Widya Michael Sofiany | D10: F | E10: Jakarta | F10: G1413 | G10: NF101 | H10: =VLOOKUP(LEFT(G10,2),Category,2,0) -> Non Food Product | I10: Personal care | J10: =VLOOKUP(LEFT(F10,1),Barcode,2,0) -> Gold | K10: 3 | L10: =INDEX($Z$8:$Z$37,MATCH(I10,$Y$8:$Y$37,0)) -> 85500 | M10: =IF(K10>8,3%,2%) -> 0.02 | N10: =HLOOKUP(VALUE(RIGHT(F10,2)),Point,2,0) -> 15 Point | O10: =(K10*L10)-(L10*M10) -> 254790 | Q10: Category | T10: Honey, jam, cereal and cheese | U10: Paper goods | V10: Comb, accessories & footwear | W10: Chilled & frozen product | Y10: Honey, jam, cereal and cheese | Z10: 155000
A11: 8 | B11: 44960 | C11: Selena Swift Widodo | D11: F | E11: Jakarta | F11: S1113 | G11: NF102 | H11: =VLOOKUP(LEFT(G11,2),Category,2,0) -> Non Food Product | I11: Baby need | J11: =VLOOKUP(LEFT(F11,1),Barcode,2,0) -> Silver | K11: 4 | L11: =INDEX($Z$8:$Z$37,MATCH(I11,$Y$8:$Y$37,0)) -> 195000 | M11: =IF(K11>8,3%,2%) -> 0.02 | N11: =HLOOKUP(VALUE(RIGHT(F11,2)),Point,2,0) -> 15 Point | O11: =(K11*L11)-(L11*M11) -> 776100 | T11: Diet & Diabeter foods | U11: Baby need | V11: Housewares & party need | W11: Fruit | Y11: Diet & Diabeter foods | Z11: 85000
A12: 9 | B12: 44960 | C12: Putri Selena Utama | D12: F | E12: Tangerang | F12: S1111 | G12: NF104 | H12: =VLOOKUP(LEFT(G12,2),Category,2,0) -> Non Food Product | I12: Baby need | J12: =VLOOKUP(LEFT(F12,1),Barcode,2,0) -> Silver | K12: 4 | L12: =INDEX($Z$8:$Z$37,MATCH(I12,$Y$8:$Y$37,0)) -> 195000 | M12: =IF(K12>8,3%,2%) -> 0.02 | N12: =HLOOKUP(VALUE(RIGHT(F12,2)),Point,2,0) -> 5 Point | O12: =(K12*L12)-(L12*M12) -> 776100 | Q12: Tabel Category | T12: Cake mix | U12: House hold | V12: Offce supplier & stationery | W12: Snack & Candy | Y12: Staple food | Z12: 55000
A13: 10 | B13: 44960 | C13: Harry Anderson | D13: M | E13: Bogor | F13: S1314 | G13: FP101 | H13: =VLOOKUP(LEFT(G13,2),Category,2,0) -> Food Product | I13: Instant Noodle & Food | J13: =VLOOKUP(LEFT(F13,1),Barcode,2,0) -> Silver | K13: 2 | L13: =INDEX($Z$8:$Z$37,MATCH(I13,$Y$8:$Y$37,0)) -> 85000 | M13: =IF(K13>8,3%,2%) -> 0.02 | N13: =HLOOKUP(VALUE(RIGHT(F13,2)),Point,2,0) -> 20 Point | O13: =(K13*L13)-(L13*M13) -> 168300 | T13: Spices, soya, sauce and ingredient | Y13: Cake mix | Z13: 125000
A14: 11 | B14: 44960 | C14: Jimmy Michael Peter | D14: M | E14: Bogor | F14: S1611 | G14: FP102 | H14: =VLOOKUP(LEFT(G14,2),Category,2,0) -> Food Product | I14: Instant Noodle & Food | J14: =VLOOKUP(LEFT(F14,1),Barcode,2,0) -> Silver | K14: 3 | L14: =INDEX($Z$8:$Z$37,MATCH(I14,$Y$8:$Y$37,0)) -> 85000 | M14: =IF(K14>8,3%,2%) -> 0.02 | N14: =HLOOKUP(VALUE(RIGHT(F14,2)),Point,2,0) -> 5 Point | O14: =(K14*L14)-(L14*M14) -> 253300 | Q14: Product ID | R14: Category | T14: Canned Food & dried meat | Y14: Spices, soya, sauce and ingredient | Z14: 95000
A15: 12 | B15: 44960 | C15: Sammy Hutagalung | D15: M | E15: Tangerang | F15: S1512 | G15: FP104 | H15: =VLOOKUP(LEFT(G15,2),Category,2,0) -> Food Product | I15: Instant Noodle & Food | J15: =VLOOKUP(LEFT(F15,1),Barcode,2,0) -> Silver | K15: 2 | L15: =INDEX($Z$8:$Z$37,MATCH(I15,$Y$8:$Y$37,0)) -> 85000 | M15: =IF(K15>8,3%,2%) -> 0.02 | N15: =HLOOKUP(VALUE(RIGHT(F15,2)),Point,2,0) -> 10 Point | O15: =(K15*L15)-(L15*M15) -> 168300 | Q15: FP | R15: Food Product | T15: Instant Noodle & Food | Y15: Canned Food & dried meat | Z15: 90000
A16: 13 | B16: 44960 | C16: Andin Dini Kusuma | D16: F | E16: Jakarta | F16: G1111 | G16: GM104 | H16: =VLOOKUP(LEFT(G16,2),Category,2,0) -> General Merchandise Product | I16: Apparel, towel and underwear | J16: =VLOOKUP(LEFT(F16,1),Barcode,2,0) -> Gold | K16: 2 | L16: =INDEX($Z$8:$Z$37,MATCH(I16,$Y$8:$Y$37,0)) -> 75000 | M16: =IF(K16>8,3%,2%) -> 0.02 | N16: =HLOOKUP(VALUE(RIGHT(F16,2)),Point,2,0) -> 5 Point | O16: =(K16*L16)-(L16*M16) -> 148500 | Q16: NF | R16: Non Food Product | T16: Milk | Y16: Instant Noodle & Food | Z16: 85000
A17: 14 | B17: 44960 | C17: Metha Viviane | D17: F | E17: Jakarta | F17: G1411 | G17: GM104 | H17: =VLOOKUP(LEFT(G17,2),Category,2,0) -> General Merchandise Product | I17: Battery, film, electrical & lamp | J17: =VLOOKUP(LEFT(F17,1),Barcode,2,0) -> Gold | K17: 3 | L17: =INDEX($Z$8:$Z$37,MATCH(I17,$Y$8:$Y$37,0)) -> 85000 | M17: =IF(K17>8,3%,2%) -> 0.02 | N17: =HLOOKUP(VALUE(RIGHT(F17,2)),Point,2,0) -> 5 Point | O17: =(K17*L17)-(L17*M17) -> 253300 | Q17: PB | R17: Perishable | T17: Baby milk & food | Y17: Milk | Z17: 70000
A18: 15 | B18: 44960 | C18: Justin Alfredo | D18: M | E18: Jakarta | F18: G1312 | G18: GM103 | H18: =VLOOKUP(LEFT(G18,2),Category,2,0) -> General Merchandise Product | I18: Battery, film, electrical & lamp | J18: =VLOOKUP(LEFT(F18,1),Barcode,2,0) -> Gold | K18: 3 | L18: =INDEX($Z$8:$Z$37,MATCH(I18,$Y$8:$Y$37,0)) -> 85000 | M18: =IF(K18>8,3%,2%) -> 0.02 | N18: =HLOOKUP(VALUE(RIGHT(F18,2)),Point,2,0) -> 10 Point | O18: =(K18*L18)-(L18*M18) -> 253300 | Q18: GM | R18: General Merchandise Product | T18: Snack, biscuit & ready to eat | Y18: Baby milk & food | Z18: 175000
A19: 16 | B19: 44960 | C19: Nicholas Agustino | D19: M | E19: Jakarta | F19: G1313 | G19: GM103 | H19: =VLOOKUP(LEFT(G19,2),Category,2,0) -> General Merchandise Product | I19: Battery, film, electrical & lamp | J19: =VLOOKUP(LEFT(F19,1),Barcode,2,0) -> Gold | K19: 7 | L19: =INDEX($Z$8:$Z$37,MATCH(I19,$Y$8:$Y$37,0)) -> 85000 | M19: =IF(K19>8,3%,2%) -> 0.02 | N19: =HLOOKUP(VALUE(RIGHT(F19,2)),Point,2,0) -> 15 Point | O19: =(K19*L19)-(L19*M19) -> 593300 | T19: Confectionary, candy & chocolate | Y19: Snack, biscuit & ready to eat | Z19: 55000
A20: 17 | B20: 44960 | C20: Chalvin Peterman | D20: M | E20: Jakarta | F20: G1311 | G20: GM103 | H20: =VLOOKUP(LEFT(G20,2),Category,2,0) -> General Merchandise Product | I20: Housewares & party need | J20: =VLOOKUP(LEFT(F20,1),Barcode,2,0) -> Gold | K20: 8 | L20: =INDEX($Z$8:$Z$37,MATCH(I20,$Y$8:$Y$37,0)) -> 110500 | M20: =IF(K20>8,3%,2%) -> 0.02 | N20: =HLOOKUP(VALUE(RIGHT(F20,2)),Point,2,0) -> 5 Point | O20: =(K20*L20)-(L20*M20) -> 881790 | T20: Cigarette & lighter | Y20: Confectionary, candy & chocolate | Z20: 65000
A21: 18 | B21: 44961 | C21: Felicia Widyotama | D21: F | E21: Jakarta | F21: P1115 | G21: GM103 | H21: =VLOOKUP(LEFT(G21,2),Category,2,0) -> General Merchandise Product | I21: Apparel, towel and underwear | J21: =VLOOKUP(LEFT(F21,1),Barcode,2,0) -> Platinum | K21: 12 | L21: =INDEX($Z$8:$Z$37,MATCH(I21,$Y$8:$Y$37,0)) -> 75000 | M21: =IF(K21>8,3%,2%) -> 0.03 | N21: =HLOOKUP(VALUE(RIGHT(F21,2)),Point,2,0) -> 25 Point | O21: =(K21*L21)-(L21*M21) -> 897750 | Q21: Member Code | T21: Medicine | Y21: Cigarette & lighter | Z21: 170000
A22: 19 | B22: 44961 | C22: Michael Anderson | D22: M | E22: Jakarta | F22: P1415 | G22: GM102 | H22: =VLOOKUP(LEFT(G22,2),Category,2,0) -> General Merchandise Product | I22: Offce supplier & stationery | J22: =VLOOKUP(LEFT(F22,1),Barcode,2,0) -> Platinum | K22: 12 | L22: =INDEX($Z$8:$Z$37,MATCH(I22,$Y$8:$Y$37,0)) -> 135500 | M22: =IF(K22>8,3%,2%) -> 0.03 | N22: =HLOOKUP(VALUE(RIGHT(F22,2)),Point,2,0) -> 25 Point | O22: =(K22*L22)-(L22*M22) -> 1621935 | Q22: Barcode | Y22: Medicine | Z22: 185000
A23: 20 | B23: 44961 | C23: Agustino Cristianaldo | D23: M | E23: Jakarta | F23: G1111 | G23: GM101 | H23: =VLOOKUP(LEFT(G23,2),Category,2,0) -> General Merchandise Product | I23: Offce supplier & stationery | J23: =VLOOKUP(LEFT(F23,1),Barcode,2,0) -> Gold | K23: 11 | L23: =INDEX($Z$8:$Z$37,MATCH(I23,$Y$8:$Y$37,0)) -> 135500 | M23: =IF(K23>8,3%,2%) -> 0.03 | N23: =HLOOKUP(VALUE(RIGHT(F23,2)),Point,2,0) -> 5 Point | O23: =(K23*L23)-(L23*M23) -> 1486435 | Q23: Member Point | Y23: Personal care | Z23: 85500
A24: 21 | B24: 44962 | C24: Aldo Alex Kusuma | D24: M | E24: Jakarta | F24: G1115 | G24: GM104 | H24: =VLOOKUP(LEFT(G24,2),Category,2,0) -> General Merchandise Product | I24: Comb, accessories & footwear | J24: =VLOOKUP(LEFT(F24,1),Barcode,2,0) -> Gold | K24: 9 | L24: =INDEX($Z$8:$Z$37,MATCH(I24,$Y$8:$Y$37,0)) -> 55500 | M24: =IF(K24>8,3%,2%) -> 0.03 | N24: =HLOOKUP(VALUE(RIGHT(F24,2)),Point,2,0) -> 25 Point | O24: =(K24*L24)-(L24*M24) -> 497835 | U24: Tabel Harga Rata-Rata Berdasarkan Category | Y24: Oral hygiene | Z24: 115000
A25: 22 | B25: 44962 | C25: Idris Jamaluddin | D25: M | E25: Tangerang | F25: G1115 | G25: FP104 | H25: =VLOOKUP(LEFT(G25,2),Category,2,0) -> Food Product | I25: Diet & Diabeter foods | J25: =VLOOKUP(LEFT(F25,1),Barcode,2,0) -> Gold | K25: 9 | L25: =INDEX($Z$8:$Z$37,MATCH(I25,$Y$8:$Y$37,0)) -> 85000 | M25: =IF(K25>8,3%,2%) -> 0.03 | N25: =HLOOKUP(VALUE(RIGHT(F25,2)),Point,2,0) -> 25 Point | O25: =(K25*L25)-(L25*M25) -> 762450 | Q25: Tabel Barcode | Y25: Paper goods | Z25: 45500
A26: 23 | B26: 44962 | C26: Irfan Haikal Fikri | D26: M | E26: Tangerang | F26: G1415 | G26: FP103 | H26: =VLOOKUP(LEFT(G26,2),Category,2,0) -> Food Product | I26: Honey, jam, cereal and cheese | J26: =VLOOKUP(LEFT(F26,1),Barcode,2,0) -> Gold | K26: 5 | L26: =INDEX($Z$8:$Z$37,MATCH(I26,$Y$8:$Y$37,0)) -> 155000 | M26: =IF(K26>8,3%,2%) -> 0.02 | N26: =HLOOKUP(VALUE(RIGHT(F26,2)),Point,2,0) -> 25 Point | O26: =(K26*L26)-(L26*M26) -> 771900 | U26: =H13 -> Food Product | V26: =AVERAGEIF($H$4:$H$183,H13,$L$4:$L$183) -> 94245.283 | Y26: Baby need | Z26: 195000
A27: 24 | B27: 44962 | C27: Hamdani Ainun Kosasih | D27: F | E27: Jakarta | F27: G1612 | G27: FP102 | H27: =VLOOKUP(LEFT(G27,2),Category,2,0) -> Food Product | I27: Snack, biscuit & ready to eat | J27: =VLOOKUP(LEFT(F27,1),Barcode,2,0) -> Gold | K27: 4 | L27: =INDEX($Z$8:$Z$37,MATCH(I27,$Y$8:$Y$37,0)) -> 55000 | M27: =IF(K27>8,3%,2%) -> 0.02 | N27: =HLOOKUP(VALUE(RIGHT(F27,2)),Point,2,0) -> 10 Point | O27: =(K27*L27)-(L27*M27) -> 218900 | Q27: Member Code | R27: Barcode | U27: =H8 -> Non Food Product | V27: =AVERAGEIF($H$4:$H$183,H8,$L$4:$L$183) -> 135627.66 | Y27: House hold | Z27: 225000
A28: 25 | B28: 44962 | C28: Haris Luthfi Yahya | D28: M | E28: Jakarta | F28: G1212 | G28: FP102 | H28: =VLOOKUP(LEFT(G28,2),Category,2,0) -> Food Product | I28: Honey, jam, cereal and cheese | J28: =VLOOKUP(LEFT(F28,1),Barcode,2,0) -> Gold | K28: 3 | L28: =INDEX($Z$8:$Z$37,MATCH(I28,$Y$8:$Y$37,0)) -> 155000 | M28: =IF(K28>8,3%,2%) -> 0.02 | N28: =HLOOKUP(VALUE(RIGHT(F28,2)),Point,2,0) -> 10 Point | O28: =(K28*L28)-(L28*M28) -> 461900 | Q28: G | R28: Gold | U28: =H16 -> General Merchandise Product | V28: =AVERAGEIF($H$4:$H$183,U28,$L$4:$L$183) -> 92558.824 | Y28: Battery, film, electrical & lamp | Z28: 85000
A29: 26 | B29: 44962 | C29: Abimanyu Abbas Hardim | D29: M | E29: Jakarta | F29: G1213 | G29: FP102 | H29: =VLOOKUP(LEFT(G29,2),Category,2,0) -> Food Product | I29: Snack, biscuit & ready to eat | J29: =VLOOKUP(LEFT(F29,1),Barcode,2,0) -> Gold | K29: 2 | L29: =INDEX($Z$8:$Z$37,MATCH(I29,$Y$8:$Y$37,0)) -> 55000 | M29: =IF(K29>8,3%,2%) -> 0.02 | N29: =HLOOKUP(VALUE(RIGHT(F29,2)),Point,2,0) -> 15 Point | O29: =(K29*L29)-(L29*M29) -> 108900 | Q29: S | R29: Silver | U29: =H4 -> Perishable | V29: =AVERAGEIF($H$4:$H$183,U29,$L$4:$L$183) -> 52731.304 | Y29: Apparel, towel and underwear | Z29: 75000
A30: 27 | B30: 44962 | C30: Sri Ratih Indah | D30: F | E30: Jakarta | F30: G1215 | G30: FP101 | H30: =VLOOKUP(LEFT(G30,2),Category,2,0) -> Food Product | I30: Medicine | J30: =VLOOKUP(LEFT(F30,1),Barcode,2,0) -> Gold | K30: 3 | L30: =INDEX($Z$8:$Z$37,MATCH(I30,$Y$8:$Y$37,0)) -> 185000 | M30: =IF(K30>8,3%,2%) -> 0.02 | N30: =HLOOKUP(VALUE(RIGHT(F30,2)),Point,2,0) -> 25 Point | O30: =(K30*L30)-(L30*M30) -> 551300 | Q30: P | R30: Platinum | Y30: Comb, accessories & footwear | Z30: 55500
A31: 28 | B31: 44962 | C31: Adeline Diany Putri | D31: F | E31: Jakarta | F31: P1214 | G31: FP101 | H31: =VLOOKUP(LEFT(G31,2),Category,2,0) -> Food Product | I31: Cigarette & lighter | J31: =VLOOKUP(LEFT(F31,1),Barcode,2,0) -> Platinum | K31: 3 | L31: =INDEX($Z$8:$Z$37,MATCH(I31,$Y$8:$Y$37,0)) -> 170000 | M31: =IF(K31>8,3%,2%) -> 0.02 | N31: =HLOOKUP(VALUE(RIGHT(F31,2)),Point,2,0) -> 20 Point | O31: =(K31*L31)-(L31*M31) -> 506600 | Y31: Housewares & party need | Z31: 110500
A32: 29 | B32: 44962 | C32: Lady Marcia Anne | D32: F | E32: Jakarta | F32: P1414 | G32: NF103 | H32: =VLOOKUP(LEFT(G32,2),Category,2,0) -> Non Food Product | I32: House hold | J32: =VLOOKUP(LEFT(F32,1),Barcode,2,0) -> Platinum | K32: 3 | L32: =INDEX($Z$8:$Z$37,MATCH(I32,$Y$8:$Y$37,0)) -> 225000 | M32: =IF(K32>8,3%,2%) -> 0.02 | N32: =HLOOKUP(VALUE(RIGHT(F32,2)),Point,2,0) -> 20 Point | O32: =(K32*L32)-(L32*M32) -> 670500 | Q32: Tabel Point | Y32: Offce supplier & stationery | Z32: 135500
A33: 30 | B33: 44962 | C33: Retno Tika Utami | D33: F | E33: Tangerang | F33: G1111 | G33: NF103 | H33: =VLOOKUP(LEFT(G33,2),Category,2,0) -> Non Food Product | I33: Paper goods | J33: =VLOOKUP(LEFT(F33,1),Barcode,2,0) -> Gold | K33: 2 | L33: =INDEX($Z$8:$Z$37,MATCH(I33,$Y$8:$Y$37,0)) -> 45500 | M33: =IF(K33>8,3%,2%) -> 0.02 | N33: =HLOOKUP(VALUE(RIGHT(F33,2)),Point,2,0) -> 5 Point | O33: =(K33*L33)-(L33*M33) -> 90090 | Y33: Eggs | Z33: 25500
A34: 31 | B34: 44962 | C34: Marcella Beverly Park Eun | D34: F | E34: Bogor | F34: G1412 | G34: NF101 | H34: =VLOOKUP(LEFT(G34,2),Category,2,0) -> Non Food Product | I34: House hold | J34: =VLOOKUP(LEFT(F34,1),Barcode,2,0) -> Gold | K34: 2 | L34: =INDEX($Z$8:$Z$37,MATCH(I34,$Y$8:$Y$37,0)) -> 225000 | M34: =IF(K34>8,3%,2%) -> 0.02 | N34: =HLOOKUP(VALUE(RIGHT(F34,2)),Point,2,0) -> 10 Point | O34: =(K34*L34)-(L34*M34) -> 445500 | Q34: Member Code | R34: 11 | S34: 12 | T34: 13 | U34: 14 | V34: 15 | Y34: Cake & bread | Z34: 49999
A35: 32 | B35: 44962 | C35: Lestari Suci Endang Kusuma | D35: F | E35: Bogor | F35: G1411 | G35: NF102 | H35: =VLOOKUP(LEFT(G35,2),Category,2,0) -> Non Food Product | I35: Paper goods | J35: =VLOOKUP(LEFT(F35,1),Barcode,2,0) -> Gold | K35: 4 | L35: =INDEX($Z$8:$Z$37,MATCH(I35,$Y$8:$Y$37,0)) -> 45500 | M35: =IF(K35>8,3%,2%) -> 0.02 | N35: =HLOOKUP(VALUE(RIGHT(F35,2)),Point,2,0) -> 5 Point | O35: =(K35*L35)-(L35*M35) -> 181090 | Q35: Member Point | R35: 5 Point | S35: 10 Point | T35: 15 Point | U35: 20 Point | V35: 25 Point | Y35: Chilled & frozen product | Z35: 69999
A36: 33 | B36: 44962 | C36: Meghan Catrine Witney | D36: F | E36: Bogor | F36: G1413 | G36: PB104 | H36: =VLOOKUP(LEFT(G36,2),Category,2,0) -> Perishable | I36: Snack & Candy | J36: =VLOOKUP(LEFT(F36,1),Barcode,2,0) -> Gold | K36: 4 | L36: =INDEX($Z$8:$Z$37,MATCH(I36,$Y$8:$Y$37,0)) -> 45555 | M36: =IF(K36>8,3%,2%) -> 0.02 | N36: =HLOOKUP(VALUE(RIGHT(F36,2)),Point,2,0) -> 15 Point | O36: =(K36*L36)-(L36*M36) -> 181308.9 | Y36: Fruit | Z36: 89999
A37: 34 | B37: 44962 | C37: Marieh Houston Stevenly | D37: F | E37: Bogor | F37: S1113 | G37: PB104 | H37: =VLOOKUP(LEFT(G37,2),Category,2,0) -> Perishable | I37: Eggs | J37: =VLOOKUP(LEFT(F37,1),Barcode,2,0) -> Silver | K37: 5 | L37: =INDEX($Z$8:$Z$37,MATCH(I37,$Y$8:$Y$37,0)) -> 25500 | M37: =IF(K37>8,3%,2%) -> 0.02 | N37: =HLOOKUP(VALUE(RIGHT(F37,2)),Point,2,0) -> 15 Point | O37: =(K37*L37)-(L37*M37) -> 126990 | Y37: Snack & Candy | Z37: 45555
A38: 35 | B38: 44962 | C38: James Leonard | D38: M | E38: Bogor | F38: S1111 | G38: PB103 | H38: =VLOOKUP(LEFT(G38,2),Category,2,0) -> Perishable | I38: Eggs | J38: =VLOOKUP(LEFT(F38,1),Barcode,2,0) -> Silver | K38: 5 | L38: =INDEX($Z$8:$Z$37,MATCH(I38,$Y$8:$Y$37,0)) -> 25500 | M38: =IF(K38>8,3%,2%) -> 0.02 | N38: =HLOOKUP(VALUE(RIGHT(F38,2)),Point,2,0) -> 5 Point | O38: =(K38*L38)-(L38*M38) -> 126990
A39: 36 | B39: 44962 | C39: Ben Bastian Budi | D39: M | E39: Bogor | F39: S1314 | G39: PB101 | H39: =VLOOKUP(LEFT(G39,2),Category,2,0) -> Perishable | I39: Fruit | J39: =VLOOKUP(LEFT(F39,1),Barcode,2,0) -> Silver | K39: 7 | L39: =INDEX($Z$8:$Z$37,MATCH(I39,$Y$8:$Y$37,0)) -> 89999 | M39: =IF(K39>8,3%,2%) -> 0.02 | N39: =HLOOKUP(VALUE(RIGHT(F39,2)),Point,2,0) -> 20 Point | O39: =(K39*L39)-(L39*M39) -> 628193.02
A40: 37 | B40: 44963 | C40: Bayu Muhammad Rinaldy | D40: M | E40: Bogor | F40: S1611 | G40: PB101 | H40: =VLOOKUP(LEFT(G40,2),Category,2,0) -> Perishable | I40: Fruit | J40: =VLOOKUP(LEFT(F40,1),Barcode,2,0) -> Silver | K40: 8 | L40: =INDEX($Z$8:$Z$37,MATCH(I40,$Y$8:$Y$37,0)) -> 89999 | M40: =IF(K40>8,3%,2%) -> 0.02 | N40: =HLOOKUP(VALUE(RIGHT(F40,2)),Point,2,0) -> 5 Point | O40: =(K40*L40)-(L40*M40) -> 718192.02
A41: 38 | B41: 44963 | C41: Rivaldo Dimas Bagus | D41: M | E41: Bogor | F41: P1115 | G41: PB101 | H41: =VLOOKUP(LEFT(G41,2),Category,2,0) -> Perishable | I41: Fruit | J41: =VLOOKUP(LEFT(F41,1),Barcode,2,0) -> Platinum | K41: 8 | L41: =INDEX($Z$8:$Z$37,MATCH(I41,$Y$8:$Y$37,0)) -> 89999 | M41: =IF(K41>8,3%,2%) -> 0.02 | N41: =HLOOKUP(VALUE(RIGHT(F41,2)),Point,2,0) -> 25 Point | O41: =(K41*L41)-(L41*M41) -> 718192.02
A42: 39 | B42: 44963 | C42: Chika Amelia Putri | D42: F | E42: Bogor | F42: S1611 | G42: PB104 | H42: =VLOOKUP(LEFT(G42,2),Category,2,0) -> Perishable | I42: Eggs | J42: =VLOOKUP(LEFT(F42,1),Barcode,2,0) -> Silver | K42: 7 | L42: =INDEX($Z$8:$Z$37,MATCH(I42,$Y$8:$Y$37,0)) -> 25500 | M42: =IF(K42>8,3%,2%) -> 0.02 | N42: =HLOOKUP(VALUE(RIGHT(F42,2)),Point,2,0) -> 5 Point | O42: =(K42*L42)-(L42*M42) -> 177990
A43: 40 | B43: 44963 | C43: Nadya Amelia Dewi Kusuma | D43: F | E43: Bogor | F43: P1115 | G43: PB104 | H43: =VLOOKUP(LEFT(G43,2),Category,2,0) -> Perishable | I43: Eggs | J43: =VLOOKUP(LEFT(F43,1),Barcode,2,0) -> Platinum | K43: 7 | L43: =INDEX($Z$8:$Z$37,MATCH(I43,$Y$8:$Y$37,0)) -> 25500 | M43: =IF(K43>8,3%,2%) -> 0.02 | N43: =HLOOKUP(VALUE(RIGHT(F43,2)),Point,2,0) -> 25 Point | O43: =(K43*L43)-(L43*M43) -> 177990
A44: 41 | B44: 44963 | C44: Raissa Februariana | D44: F | E44: Tangerang | F44: P1415 | G44: PB103 | H44: =VLOOKUP(LEFT(G44,2),Category,2,0) -> Perishable | I44: Eggs | J44: =VLOOKUP(LEFT(F44,1),Barcode,2,0) -> Platinum | K44: 5 | L44: =INDEX($Z$8:$Z$37,MATCH(I44,$Y$8:$Y$37,0)) -> 25500 | M44: =IF(K44>8,3%,2%) -> 0.02 | N44: =HLOOKUP(VALUE(RIGHT(F44,2)),Point,2,0) -> 25 Point | O44: =(K44*L44)-(L44*M44) -> 126990
A45: 42 | B45: 44963 | C45: Annisa Fajar Utama | D45: F | E45: Tangerang | F45: P1115 | G45: PB103 | H45: =VLOOKUP(LEFT(G45,2),Category,2,0) -> Perishable | I45: Eggs | J45: =VLOOKUP(LEFT(F45,1),Barcode,2,0) -> Platinum | K45: 4 | L45: =INDEX($Z$8:$Z$37,MATCH(I45,$Y$8:$Y$37,0)) -> 25500 | M45: =IF(K45>8,3%,2%) -> 0.02 | N45: =HLOOKUP(VALUE(RIGHT(F45,2)),Point,2,0) -> 25 Point | O45: =(K45*L45)-(L45*M45) -> 101490
A46: 43 | B46: 44964 | C46: Hadi Kusumaningrum | D46: M | E46: Tangerang | F46: P1415 | G46: GM101 | H46: =VLOOKUP(LEFT(G46,2),Category,2,0) -> General Merchandise Product | I46: Housewares & party need | J46: =VLOOKUP(LEFT(F46,1),Barcode,2,0) -> Platinum | K46: 6 | L46: =INDEX($Z$8:$Z$37,MATCH(I46,$Y$8:$Y$37,0)) -> 110500 | M46: =IF(K46>8,3%,2%) -> 0.02 | N46: =HLOOKUP(VALUE(RIGHT(F46,2)),Point,2,0) -> 25 Point | O46: =(K46*L46)-(L46*M46) -> 660790
A47: 44 | B47: 44964 | C47: Wulandari Septiansyah | D47: F | E47: Tangerang | F47: P1115 | G47: GM104 | H47: =VLOOKUP(LEFT(G47,2),Category,2,0) -> General Merchandise Product | I47: Offce supplier & stationery | J47: =VLOOKUP(LEFT(F47,1),Barcode,2,0) -> Platinum | K47: 8 | L47: =INDEX($Z$8:$Z$37,MATCH(I47,$Y$8:$Y$37,0)) -> 135500 | M47: =IF(K47>8,3%,2%) -> 0.02 | N47: =HLOOKUP(VALUE(RIGHT(F47,2)),Point,2,0) -> 25 Point | O47: =(K47*L47)-(L47*M47) -> 1081290
A48: 45 | B48: 44964 | C48: Esmeralda Tika Kusuma | D48: F | E48: Tangerang | F48: P1415 | G48: FP104 | H48: =VLOOKUP(LEFT(G48,2),Category,2,0) -> Food Product | I48: Baby milk & food | J48: =VLOOKUP(LEFT(F48,1),Barcode,2,0) -> Platinum | K48: 8 | L48: =INDEX($Z$8:$Z$37,MATCH(I48,$Y$8:$Y$37,0)) -> 175000 | M48: =IF(K48>8,3%,2%) -> 0.02 | N48: =HLOOKUP(VALUE(RIGHT(F48,2)),Point,2,0) -> 25 Point | O48: =(K48*L48)-(L48*M48) -> 1396500
A49: 46 | B49: 44964 | C49: Tristan Toni Tobing | D49: M | E49: Jakarta | F49: G1111 | G49: FP103 | H49: =VLOOKUP(LEFT(G49,2),Category,2,0) -> Food Product | I49: Confectionary, candy & chocolate | J49: =VLOOKUP(LEFT(F49,1),Barcode,2,0) -> Gold | K49: 9 | L49: =INDEX($Z$8:$Z$37,MATCH(I49,$Y$8:$Y$37,0)) -> 65000 | M49: =IF(K49>8,3%,2%) -> 0.03 | N49: =HLOOKUP(VALUE(RIGHT(F49,2)),Point,2,0) -> 5 Point | O49: =(K49*L49)-(L49*M49) -> 583050
... A183: 180 | B183: 44990 | C183: Milaney Wangsa Widyatama | D183: F | E183: Bekasi | F183: S1113 | G183: NF104 | H183: =VLOOKUP(LEFT(G183,2),Category,2,0) -> Non Food Product | I183: Personal care | J183: =VLOOKUP(LEFT(F183,1),Barcode,2,0) -> Silver | K183: 8 | L183: =INDEX($Z$8:$Z$37,MATCH(I183,$Y$8:$Y$37,0)) -> 85500 | M183: =IF(K183>8,3%,2%) -> 0.02 | N183: =HLOOKUP(VALUE(RIGHT(F183,2)),Point,2,0) -> 15 Point | O183: =(K183*L183)-(L183*M183) -> 682290
J184: Total Quantity | K184: =SUM(K4:K183) -> 1100 | N184: Total Payment | O184: =SUM(O4:O183) -> 1.0482789e+08
N185: Rata-rata Payment | O185: =AVERAGE(O4:O183) -> 582377.16

Sheet Pivot Table
A1: Total Pembayaran Berdasarkan Jenis Kelamin dan Category
A3: Total Pembayaran | B3: Category
A4: Gender | B4: Food Product | C4: General Merchandise Product | D4: Non Food Product | E4: Perishable | F4: Grand Total
A5: F | B5: 19422150 | C5: 9955125 | D5: 25900255 | E5: 7369830.1 | F5: 62647360
A6: M | B6: 12945000 | C6: 10556965 | D6: 12724775 | E6: 5953788.1 | F6: 42180528
A7: Grand Total | B7: 32367150 | C7: 20512090 | D7: 38625030 | E7: 13323618 | F7: 1.0482789e+08 | AC7: *Stacked Colomn Chart
O12: *Slicer Dapat digunakan Untuk Filter Semua Table
B16: Jumlah Barang Terjual Berdasarkan Domisili dan Product ID
A19: Total Quantity | B19: Product ID
A20: Domisili | B20: FP101 | C20: FP102 | D20: FP103 | E20: FP104 | F20: GM101 | G20: GM102 | H20: GM103 | I20: GM104 | J20: NF101 | K20: NF102 | L20: NF103 | M20: NF104 | N20: PB101 | O20: PB102 | P20: PB103 | Q20: PB104 | R20: Grand Total
A21: Bandung | P21: 8 | R21: 8
A22: Bekasi | B22: 9 | C22: 8 | E22: 51 | H22: 26 | J22: 29 | K22: 12 | M22: 37 | O22: 16 | R22: 188
A23: Bogor | B23: 36 | C23: 11 | E23: 19 | G23: 5 | H23: 32 | I23: 7 | J23: 11 | K23: 4 | L23: 9 | M23: 14 | N23: 31 | O23: 17 | P23: 5 | Q23: 23 | R23: 224
A24: Jakarta | B24: 27 | C24: 47 | D24: 9 | E24: 21 | F24: 16 | G24: 12 | H24: 58 | I24: 26 | J24: 47 | K24: 11 | L24: 19 | M24: 46 | N24: 2 | O24: 63 | P24: 19 | Q24: 4 | R24: 427
A25: Tangerang | B25: 15 | C25: 42 | D25: 17 | E25: 33 | F25: 14 | I25: 19 | J25: 22 | K25: 15 | L25: 6 | M25: 17 | N25: 11 | P25: 28 | Q25: 14 | R25: 253
A26: Grand Total | B26: 87 | C26: 108 | D26: 26 | E26: 124 | F26: 30 | G26: 17 | H26: 116 | I26: 52 | J26: 109 | K26: 42 | L26: 34 | M26: 114 | N26: 44 | O26: 96 | P26: 60 | Q26: 41 | R26: 1100 | AC26: *Clusterd Bar Chart
B29: Rata-Rata Harga Per item Berdasarkan Nama Produk dan Membership
A34: Rata-Rata Harga Per Item | B34: Member
A35: Nama Produk | B35: Gold | C35: Platinum | D35: Silver | E35: Grand Total
A36: Apparel, towel and underwear | B36: 75000 | C36: 75000 | E36: 75000
A37: Baby milk & food | C37: 175000 | E37: 175000
A38: Baby need | B38: 195000 | C38: 195000 | D38: 195000 | E38: 195000
A39: Battery, film, electrical & lamp | B39: 85000 | C39: 85000 | D39: 85000 | E39: 85000
A40: Beverage | B40: 75000 | C40: 75000 | D40: 75000 | E40: 75000
A41: Cake & bread | B41: 49999 | C41: 49999 | D41: 49999 | E41: 49999
A42: Cake mix | B42: 125000 | E42: 125000
A43: Canned Food & dried meat | B43: 90000 | E43: 90000
A44: Chilled & frozen product | B44: 69999 | C44: 69999 | E44: 69999
A45: Cigarette & lighter | C45: 170000 | E45: 170000
A46: Comb, accessories & footwear | B46: 55500 | E46: 55500
A47: Confectionary, candy & chocolate | B47: 65000 | D47: 65000 | E47: 65000
A48: Diet & Diabeter foods | B48: 85000 | E48: 85000
A49: Eggs | B49: 25500 | C49: 25500 | D49: 25500 | E49: 25500
A50: Fruit | B50: 89999 | C50: 89999 | D50: 89999 | E50: 89999
A51: Honey, jam, cereal and cheese | B51: 155000 | E51: 155000
A52: House hold | B52: 225000 | C52: 225000 | D52: 225000 | E52: 225000
A53: Housewares & party need | B53: 110500 | C53: 110500 | E53: 110500
A54: Instant Noodle & Food | D54: 85000 | E54: 85000
A55: Medicine | B55: 185000 | E55: 185000
A56: Milk | B56: 70000 | E56: 70000
A57: Offce supplier & stationery | B57: 135500 | C57: 135500 | E57: 135500
A58: Oral hygiene | B58: 115000 | C58: 115000 | D58: 115000 | E58: 115000
A59: Paper goods | B59: 45500 | C59: 45500 | D59: 45500 | E59: 45500 | AC59: *Line Chart
A60: Personal care | B60: 85500 | C60: 85500 | D60: 85500 | E60: 85500
A61: Snack & Candy | B61: 45555 | D61: 45555 | E61: 45555
A62: Snack, biscuit & ready to eat | B62: 55000 | C62: 55000 | D62: 55000 | E62: 55000
A63: Spices, soya, sauce and ingredient | B63: 95000 | D63: 95000 | E63: 95000
A64: Tea, coffee and creamer | B64: 120000 | D64: 120000 | E64: 120000
A65: Grand Total | B65: 89995.446 | C65: 103049.82 | D65: 95656.59 | E65: 94123
B67: Total Pengguna (Membership) Berdasarkan Gender dan Domisili
A69: Membership | B69: Gender
A70: Domisili | B70: F | C70: M | D70: Grand Total
A71: Bandung | B71: 1 | D71: 1
A72: Bekasi | B72: 17 | C72: 13 | D72: 30
A73: Bogor | B73: 25 | C73: 14 | D73: 39
A74: Jakarta | B74: 41 | C74: 31 | D74: 72
A75: Tangerang | B75: 25 | C75: 13 | D75: 38
A76: Grand Total | B76: 109 | C76: 71 | D76: 180
A78: F = Female
A79: M = Male
AC89: *Pie Chart

Sheet Data Table Analysis
A3: Data Table
I4: Accumulation Expense (Payment Period of rent space) | O4: Product ID | P4: Category | Q4: Name of Product | R4: Quantity | S4: Price item | T4: Tax | U4: Total Payment | V4: Category | W4: Inventory | X4: Update | Y4: Total Product
A5: Total Quantity Item | B5: ='Master (Filled)'!K184 -> 1100 | O5: PB103 | P5: Perishable | Q5: Cake & bread | R5: 5 | S5: =INDEX('Master (Filled)'!$Z$8:$Z$37,MATCH(Q5,'Master (Filled)'!$Y$8:$Y$37,0)) -> 49999 | T5: =IF(R5>8,3%,2%) -> 0.02 | U5: =(R5*S5)-(S5*T5) -> 248995.02 | V5: Perishable | W5: =IF(Q5="Food Product",700,IF(Q5="Non Food Product",900,IF(Q5="General Merchandise Product",855,755))) -> 755 | X5: =SUMIF(Table1316[Category],Table1417[[#This Row],[Category]],Table1316[[Quantity ]]) -> 241 | Y5: =Table1417[[#This Row],[Inventory]]-Table1417[[#This Row],[Update ]] -> 514
A6: Average Price | B6: ='Master (Filled)'!O185 -> 582377.16 | I6: Installment | J6: 200000000 | O6: PB101 | P6: Perishable | Q6: Chilled & frozen product | R6: 8 | S6: =INDEX('Master (Filled)'!$Z$8:$Z$37,MATCH(Q6,'Master (Filled)'!$Y$8:$Y$37,0)) -> 69999 | T6: =IF(R6>8,3%,2%) -> 0.02 | U6: =(R6*S6)-(S6*T6) -> 558592.02 | V6: Perishable | W6: =IF(Q6="Food Product",700,IF(Q6="Non Food Product",900,IF(Q6="General Merchandise Product",855,755))) -> 755 | X6: =SUMIF(Table1316[Category],Table1417[[#This Row],[Category]],Table1316[[Quantity ]]) -> 241 | Y6: =Table1417[[#This Row],[Inventory]]-Table1417[[#This Row],[Update ]] -> 514
A7: Service Tax | B7: 0.03 | I7: Periodic of installment | J7: 20 | K7: =J7/J9 -> 1.6666667 | O7: PB103 | P7: Perishable | Q7: Cake & bread | R7: 8 | S7: =INDEX('Master (Filled)'!$Z$8:$Z$37,MATCH(Q7,'Master (Filled)'!$Y$8:$Y$37,0)) -> 49999 | T7: =IF(R7>8,3%,2%) -> 0.02 | U7: =(R7*S7)-(S7*T7) -> 398992.02 | V7: Perishable | W7: =IF(Q7="Food Product",700,IF(Q7="Non Food Product",900,IF(Q7="General Merchandise Product",855,755))) -> 755 | X7: =SUMIF(Table1316[Category],Table1417[[#This Row],[Category]],Table1316[[Quantity ]]) -> 241 | Y7: =Table1417[[#This Row],[Inventory]]-Table1417[[#This Row],[Update ]] -> 514
A8: Estimated Income | B8: =B6*B5 -> 6.4061487e+08 | C8: *Average Price x Total Quantity Item | I8: Lease interest expense | J8: 12 | K8: =J8/12 -> 1 | O8: PB102 | P8: Perishable | Q8: Eggs | R8: 2 | S8: =INDEX('Master (Filled)'!$Z$8:$Z$37,MATCH(Q8,'Master (Filled)'!$Y$8:$Y$37,0)) -> 25500 | T8: =IF(R8>8,3%,2%) -> 0.02 | U8: =(R8*S8)-(S8*T8) -> 50490 | V8: Perishable | W8: =IF(Q8="Food Product",700,IF(Q8="Non Food Product",900,IF(Q8="General Merchandise Product",855,755))) -> 755 | X8: =SUMIF(Table1316[Category],Table1417[[#This Row],[Category]],Table1316[[Quantity ]]) -> 241 | Y8: =Table1417[[#This Row],[Inventory]]-Table1417[[#This Row],[Update ]] -> 514
A9: Income After Tax | B9: =(B8*B7)+B8 -> 6.5983332e+08 | C9: *(Estimated Income x Service Tax) + Estimated Income | I9: Periodic on Year | J9: 12 | O9: NF104 | P9: Non Food Product | Q9: Baby need | R9: 2 | S9: =INDEX('Master (Filled)'!$Z$8:$Z$37,MATCH(Q9,'Master (Filled)'!$Y$8:$Y$37,0)) -> 195000 | T9: =IF(R9>8,3%,2%) -> 0.02 | U9: =(R9*S9)-(S9*T9) -> 386100 | V9: Non Food Product | W9: =IF(Q9="Food Product",700,IF(Q9="Non Food Product",900,IF(Q9="General Merchandise Product",855,755))) -> 755 | X9: =SUMIF(Table1316[Category],Table1417[[#This Row],[Category]],Table1316[[Quantity ]]) -> 299 | Y9: =Table1417[[#This Row],[Inventory]]-Table1417[[#This Row],[Update ]] -> 456
O10: NF101 | P10: Non Food Product | Q10: Personal care | R10: 2 | S10: =INDEX('Master (Filled)'!$Z$8:$Z$37,MATCH(Q10,'Master (Filled)'!$Y$8:$Y$37,0)) -> 85500 | T10: =IF(R10>8,3%,2%) -> 0.02 | U10: =(R10*S10)-(S10*T10) -> 169290 | V10: Non Food Product | W10: =IF(Q10="Food Product",700,IF(Q10="Non Food Product",900,IF(Q10="General Merchandise Product",855,755))) -> 755 | X10: =SUMIF(Table1316[Category],Table1417[[#This Row],[Category]],Table1316[[Quantity ]]) -> 299 | Y10: =Table1417[[#This Row],[Inventory]]-Table1417[[#This Row],[Update ]] -> 456
O11: NF101 | P11: Non Food Product | Q11: Personal care | R11: 3 | S11: =INDEX('Master (Filled)'!$Z$8:$Z$37,MATCH(Q11,'Master (Filled)'!$Y$8:$Y$37,0)) -> 85500 | T11: =IF(R11>8,3%,2%) -> 0.02 | U11: =(R11*S11)-(S11*T11) -> 254790 | V11: Non Food Product | W11: =IF(Q11="Food Product",700,IF(Q11="Non Food Product",900,IF(Q11="General Merchandise Product",855,755))) -> 755 | X11: =SUMIF(Table1316[Category],Table1417[[#This Row],[Category]],Table1316[[Quantity ]]) -> 299 | Y11: =Table1417[[#This Row],[Inventory]]-Table1417[[#This Row],[Update ]] -> 456
I12: Payment of Installment | J12: Interest | K12: Principal | L12: Total Debt | O12: NF102 | P12: Non Food Product | Q12: Baby need | R12: 4 | S12: =INDEX('Master (Filled)'!$Z$8:$Z$37,MATCH(Q12,'Master (Filled)'!$Y$8:$Y$37,0)) -> 195000 | T12: =IF(R12>8,3%,2%) -> 0.02 | U12: =(R12*S12)-(S12*T12) -> 776100 | V12: Non Food Product | W12: =IF(Q12="Food Product",700,IF(Q12="Non Food Product",900,IF(Q12="General Merchandise Product",855,755))) -> 755 | X12: =SUMIF(Table1316[Category],Table1417[[#This Row],[Category]],Table1316[[Quantity ]]) -> 299 | Y12: =Table1417[[#This Row],[Inventory]]-Table1417[[#This Row],[Update ]] -> 456
A13: Skenario : Jika Ingin Mencapai Target Keuntungan IDR 250 JT | L13: =J6 -> 200000000 | O13: NF104 | P13: Non Food Product | Q13: Baby need | R13: 4 | S13: =INDEX('Master (Filled)'!$Z$8:$Z$37,MATCH(Q13,'Master (Filled)'!$Y$8:$Y$37,0)) -> 195000 | T13: =IF(R13>8,3%,2%) -> 0.02 | U13: =(R13*S13)-(S13*T13) -> 776100 | V13: Non Food Product | W13: =IF(Q13="Food Product",700,IF(Q13="Non Food Product",900,IF(Q13="General Merchandise Product",855,755))) -> 755 | X13: =SUMIF(Table1316[Category],Table1417[[#This Row],[Category]],Table1316[[Quantity ]]) -> 299 | Y13: =Table1417[[#This Row],[Inventory]]-Table1417[[#This Row],[Update ]] -> 456
I14: 1 | J14: =IPMT($K8%,$I$14,$J$7,$L$13) -> -2000000 | K14: =-PPMT($K8%,$I$14,$J$7,$L$13) -> 9083063 | L14: =L13-K14 -> 1.9091694e+08 | O14: FP101 | P14: Food Product | Q14: Instant Noodle & Food | R14: 2 | S14: =INDEX('Master (Filled)'!$Z$8:$Z$37,MATCH(Q14,'Master (Filled)'!$Y$8:$Y$37,0)) -> 85000 | T14: =IF(R14>8,3%,2%) -> 0.02 | U14: =(R14*S14)-(S14*T14) -> 168300 | V14: Food Product | W14: =IF(Q14="Food Product",700,IF(Q14="Non Food Product",900,IF(Q14="General Merchandise Product",855,755))) -> 755 | X14: =SUMIF(Table1316[Category],Table1417[[#This Row],[Category]],Table1316[[Quantity ]]) -> 345 | Y14: =Table1417[[#This Row],[Inventory]]-Table1417[[#This Row],[Update ]] -> 410
A15: Total Quantity Item | B15: =B5 -> 1100 | D15: Quantity | E15: 4672.8972 | I15: 2 | J15: =IPMT($K8%,$I$15,$J$7,$L$13) -> -1909169.4 | K15: =-PPMT($K8%,$I$15,$J$7,$L$13) -> 9173893.6 | L15: =L14-K15 -> 1.8174304e+08 | O15: FP102 | P15: Food Product | Q15: Instant Noodle & Food | R15: 3 | S15: =INDEX('Master (Filled)'!$Z$8:$Z$37,MATCH(Q15,'Master (Filled)'!$Y$8:$Y$37,0)) -> 85000 | T15: =IF(R15>8,3%,2%) -> 0.02 | U15: =(R15*S15)-(S15*T15) -> 253300 | V15: Food Product | W15: =IF(Q15="Food Product",700,IF(Q15="Non Food Product",900,IF(Q15="General Merchandise Product",855,755))) -> 755 | X15: =SUMIF(Table1316[Category],Table1417[[#This Row],[Category]],Table1316[[Quantity ]]) -> 345 | Y15: =Table1417[[#This Row],[Inventory]]-Table1417[[#This Row],[Update ]] -> 410
A16: Average Price | B16: =B6 -> 582377.16 | D16: Price | E16: 75000 | I16: 3 | J16: =IPMT($K8%,$I$16,$J$7,$L$13) -> -1817430.4 | K16: =-PPMT($K8%,$I$16,$J$7,$L$13) -> 9265632.5 | L16: =L15-K16 -> 1.7247741e+08 | O16: FP104 | P16: Food Product | Q16: Instant Noodle & Food | R16: 2 | S16: =INDEX('Master (Filled)'!$Z$8:$Z$37,MATCH(Q16,'Master (Filled)'!$Y$8:$Y$37,0)) -> 85000 | T16: =IF(R16>8,3%,2%) -> 0.02 | U16: =(R16*S16)-(S16*T16) -> 168300 | V16: Food Product | W16: =IF(Q16="Food Product",700,IF(Q16="Non Food Product",900,IF(Q16="General Merchandise Product",855,755))) -> 755 | X16: =SUMIF(Table1316[Category],Table1417[[#This Row],[Category]],Table1316[[Quantity ]]) -> 345 | Y16: =Table1417[[#This Row],[Inventory]]-Table1417[[#This Row],[Update ]] -> 410
A17: Service Tax | B17: =B7 -> 0.03 | D17: Total Sales | E17: =E16*E15 -> 3.5046729e+08 | F17: *Price x Quantity | I17: 4 | J17: =IPMT($K8%,$I$17,$J$7,$L$13) -> -1724774.1 | K17: =-PPMT($K8%,$I$17,$J$7,$L$13) -> 9358288.9 | L17: =L16-K17 -> 1.6311912e+08 | O17: GM104 | P17: General Merchandise Product | Q17: Apparel, towel and underwear | R17: 2 | S17: =INDEX('Master (Filled)'!$Z$8:$Z$37,MATCH(Q17,'Master (Filled)'!$Y$8:$Y$37,0)) -> 75000 | T17: =IF(R17>8,3%,2%) -> 0.02 | U17: =(R17*S17)-(S17*T17) -> 148500 | V17: General Merchandise Product | W17: =IF(Q17="Food Product",700,IF(Q17="Non Food Product",900,IF(Q17="General Merchandise Product",855,755))) -> 755 | X17: =SUMIF(Table1316[Category],Table1417[[#This Row],[Category]],Table1316[[Quantity ]]) -> 215 | Y17: =Table1417[[#This Row],[Inventory]]-Table1417[[#This Row],[Update ]] -> 540
A18: Estimated Income | B18: =B8 -> 6.4061487e+08 | I18: 5 | J18: =IPMT($K8%,$I$18,$J$7,$L$13) -> -1631191.2 | K18: =-PPMT($K8%,$I$18,$J$7,$L$13) -> 9451871.8 | L18: =L17-K18 -> 1.5366725e+08 | O18: GM104 | P18: General Merchandise Product | Q18: Battery, film, electrical & lamp | R18: 3 | S18: =INDEX('Master (Filled)'!$Z$8:$Z$37,MATCH(Q18,'Master (Filled)'!$Y$8:$Y$37,0)) -> 85000 | T18: =IF(R18>8,3%,2%) -> 0.02 | U18: =(R18*S18)-(S18*T18) -> 253300 | V18: General Merchandise Product | W18: =IF(Q18="Food Product",700,IF(Q18="Non Food Product",900,IF(Q18="General Merchandise Product",855,755))) -> 755 | X18: =SUMIF(Table1316[Category],Table1417[[#This Row],[Category]],Table1316[[Quantity ]]) -> 215 | Y18: =Table1417[[#This Row],[Inventory]]-Table1417[[#This Row],[Update ]] -> 540
A19: Income After Tax | B19: =B9 -> 6.5983332e+08 | D19: Expense (Pengeluaran) | I19: 6 | J19: =IPMT($K8%,$I$19,$J$7,$L$13) -> -1536672.5 | K19: =-PPMT($K8%,$I$19,$J$7,$L$13) -> 9546390.5 | L19: =L18-K19 -> 1.4412086e+08 | O19: GM103 | P19: General Merchandise Product | Q19: Battery, film, electrical & lamp | R19: 3 | S19: =INDEX('Master (Filled)'!$Z$8:$Z$37,MATCH(Q19,'Master (Filled)'!$Y$8:$Y$37,0)) -> 85000 | T19: =IF(R19>8,3%,2%) -> 0.02 | U19: =(R19*S19)-(S19*T19) -> 253300 | V19: General Merchandise Product | W19: =IF(Q19="Food Product",700,IF(Q19="Non Food Product",900,IF(Q19="General Merchandise Product",855,755))) -> 755 | X19: =SUMIF(Table1316[Category],Table1417[[#This Row],[Category]],Table1316[[Quantity ]]) -> 215 | Y19: =Table1417[[#This Row],[Inventory]]-Table1417[[#This Row],[Update ]] -> 540
D20: Producing Expense | E20: 13000 | I20: 7 | J20: =IPMT($K8%,$I$20,$J$7,$L$13) -> -1441208.6 | K20: =-PPMT($K8%,$I$20,$J$7,$L$13) -> 9641854.4 | L20: =L19-K20 -> 1.3447901e+08 | O20: GM103 | P20: General Merchandise Product | Q20: Battery, film, electrical & lamp | R20: 7 | S20: =INDEX('Master (Filled)'!$Z$8:$Z$37,MATCH(Q20,'Master (Filled)'!$Y$8:$Y$37,0)) -> 85000 | T20: =IF(R20>8,3%,2%) -> 0.02 | U20: =(R20*S20)-(S20*T20) -> 593300 | V20: General Merchandise Product | W20: =IF(Q20="Food Product",700,IF(Q20="Non Food Product",900,IF(Q20="General Merchandise Product",855,755))) -> 755 | X20: =SUMIF(Table1316[Category],Table1417[[#This Row],[Category]],Table1316[[Quantity ]]) -> 215 | Y20: =Table1417[[#This Row],[Inventory]]-Table1417[[#This Row],[Update ]] -> 540
D21: Packaging Expense | E21: 8500 | I21: 8 | J21: =IPMT($K8%,$I$21,$J$7,$L$13) -> -1344790.1 | K21: =-PPMT($K8%,$I$21,$J$7,$L$13) -> 9738272.9 | L21: =L20-K21 -> 1.2474073e+08 | O21: GM103 | P21: General Merchandise Product | Q21: Housewares & party need | R21: 8 | S21: =INDEX('Master (Filled)'!$Z$8:$Z$37,MATCH(Q21,'Master (Filled)'!$Y$8:$Y$37,0)) -> 110500 | T21: =IF(R21>8,3%,2%) -> 0.02 | U21: =(R21*S21)-(S21*T21) -> 881790 | V21: General Merchandise Product | W21: =IF(Q21="Food Product",700,IF(Q21="Non Food Product",900,IF(Q21="General Merchandise Product",855,755))) -> 755 | X21: =SUMIF(Table1316[Category],Table1417[[#This Row],[Category]],Table1316[[Quantity ]]) -> 215 | Y21: =Table1417[[#This Row],[Inventory]]-Table1417[[#This Row],[Update ]] -> 540
A22: Expense (Pengeluaran) | D22: Total Expense(2) | E22: =(E20*E15)+(E21*E15) -> 1.0046729e+08 | F22: *(Producing Expense x Quantity) + (Packaging Expense * Quantity) | I22: 9 | J22: =IPMT($K8%,$I$22,$J$7,$L$13) -> -1247407.3 | K22: =-PPMT($K8%,$I$22,$J$7,$L$13) -> 9835655.7 | L22: =L21-K22 -> 1.1490508e+08 | O22: GM103 | P22: General Merchandise Product | Q22: Apparel, towel and underwear | R22: 12 | S22: =INDEX('Master (Filled)'!$Z$8:$Z$37,MATCH(Q22,'Master (Filled)'!$Y$8:$Y$37,0)) -> 75000 | T22: =IF(R22>8,3%,2%) -> 0.03 | U22: =(R22*S22)-(S22*T22) -> 897750 | V22: General Merchandise Product | W22: =IF(Q22="Food Product",700,IF(Q22="Non Food Product",900,IF(Q22="General Merchandise Product",855,755))) -> 755 | X22: =SUMIF(Table1316[Category],Table1417[[#This Row],[Category]],Table1316[[Quantity ]]) -> 215 | Y22: =Table1417[[#This Row],[Inventory]]-Table1417[[#This Row],[Update ]] -> 540
I23: 10 | J23: =IPMT($K8%,$I$23,$J$7,$L$13) -> -1149050.8 | K23: =-PPMT($K8%,$I$23,$J$7,$L$13) -> 9934012.2 | L23: =L22-K23 -> 1.0497106e+08 | O23: GM102 | P23: General Merchandise Product | Q23: Offce supplier & stationery | R23: 12 | S23: =INDEX('Master (Filled)'!$Z$8:$Z$37,MATCH(Q23,'Master (Filled)'!$Y$8:$Y$37,0)) -> 135500 | T23: =IF(R23>8,3%,2%) -> 0.03 | U23: =(R23*S23)-(S23*T23) -> 1621935 | V23: General Merchandise Product | W23: =IF(Q23="Food Product",700,IF(Q23="Non Food Product",900,IF(Q23="General Merchandise Product",855,755))) -> 755 | X23: =SUMIF(Table1316[Category],Table1417[[#This Row],[Category]],Table1316[[Quantity ]]) -> 215 | Y23: =Table1417[[#This Row],[Inventory]]-Table1417[[#This Row],[Update ]] -> 540
A24: Fixed Cost | B24: 8000 | I24: 11 | J24: =IPMT($K8%,$I$24,$J$7,$L$13) -> -1049710.6 | K24: =-PPMT($K8%,$I$24,$J$7,$L$13) -> 10033352 | L24: =L23-K24 -> 94937712 | O24: GM101 | P24: General Merchandise Product | Q24: Offce supplier & stationery | R24: 11 | S24: =INDEX('Master (Filled)'!$Z$8:$Z$37,MATCH(Q24,'Master (Filled)'!$Y$8:$Y$37,0)) -> 135500 | T24: =IF(R24>8,3%,2%) -> 0.03 | U24: =(R24*S24)-(S24*T24) -> 1486435 | V24: General Merchandise Product | W24: =IF(Q24="Food Product",700,IF(Q24="Non Food Product",900,IF(Q24="General Merchandise Product",855,755))) -> 755 | X24: =SUMIF(Table1316[Category],Table1417[[#This Row],[Category]],Table1316[[Quantity ]]) -> 215 | Y24: =Table1417[[#This Row],[Inventory]]-Table1417[[#This Row],[Update ]] -> 540
A25: Variable Cost | B25: 11000 | I25: 12 | J25: =IPMT($K8%,$I$25,$J$7,$L$13) -> -949377.12 | K25: =-PPMT($K8%,$I$25,$J$7,$L$13) -> 10133686 | L25: =L24-K25 -> 84804026 | O25: GM104 | P25: General Merchandise Product | Q25: Comb, accessories & footwear | R25: 9 | S25: =INDEX('Master (Filled)'!$Z$8:$Z$37,MATCH(Q25,'Master (Filled)'!$Y$8:$Y$37,0)) -> 55500 | T25: =IF(R25>8,3%,2%) -> 0.03 | U25: =(R25*S25)-(S25*T25) -> 497835 | V25: General Merchandise Product | W25: =IF(Q25="Food Product",700,IF(Q25="Non Food Product",900,IF(Q25="General Merchandise Product",855,755))) -> 755 | X25: =SUMIF(Table1316[Category],Table1417[[#This Row],[Category]],Table1316[[Quantity ]]) -> 215 | Y25: =Table1417[[#This Row],[Inventory]]-Table1417[[#This Row],[Update ]] -> 540
A26: Total Expense (1) | B26: =(B24*B5)+(B25*B5) -> 20900000 | C26: *(Fixed Cost x Total Quantity Item) + (Variable Cost*Total Quantity Item) | I26: 13 | J26: =IPMT($K8%,$I$26,$J$7,$L$13) -> -848040.26 | K26: =-PPMT($K8%,$I$26,$J$7,$L$13) -> 10235023 | L26: =L25-K26 -> 74569004 | O26: FP104 | P26: Food Product | Q26: Diet & Diabeter foods | R26: 9 | S26: =INDEX('Master (Filled)'!$Z$8:$Z$37,MATCH(Q26,'Master (Filled)'!$Y$8:$Y$37,0)) -> 85000 | T26: =IF(R26>8,3%,2%) -> 0.03 | U26: =(R26*S26)-(S26*T26) -> 762450 | V26: Food Product | W26: =IF(Q26="Food Product",700,IF(Q26="Non Food Product",900,IF(Q26="General Merchandise Product",855,755))) -> 755 | X26: =SUMIF(Table1316[Category],Table1417[[#This Row],[Category]],Table1316[[Quantity ]]) -> 345 | Y26: =Table1417[[#This Row],[Inventory]]-Table1417[[#This Row],[Update ]] -> 410
I27: 14 | J27: =IPMT($K8%,$I$27,$J$7,$L$13) -> -745690.04 | K27: =-PPMT($K8%,$I$27,$J$7,$L$13) -> 10337373 | L27: =L26-K27 -> 64231631 | O27: FP103 | P27: Food Product | Q27: Honey, jam, cereal and cheese | R27: 5 | S27: =INDEX('Master (Filled)'!$Z$8:$Z$37,MATCH(Q27,'Master (Filled)'!$Y$8:$Y$37,0)) -> 155000 | T27: =IF(R27>8,3%,2%) -> 0.02 | U27: =(R27*S27)-(S27*T27) -> 771900 | V27: Food Product | W27: =IF(Q27="Food Product",700,IF(Q27="Non Food Product",900,IF(Q27="General Merchandise Product",855,755))) -> 755 | X27: =SUMIF(Table1316[Category],Table1417[[#This Row],[Category]],Table1316[[Quantity ]]) -> 345 | Y27: =Table1417[[#This Row],[Inventory]]-Table1417[[#This Row],[Update ]] -> 410
I28: 15 | J28: =IPMT($K8%,$I$28,$J$7,$L$13) -> -642316.31 | K28: =-PPMT($K8%,$I$28,$J$7,$L$13) -> 10440747 | L28: =L27-K28 -> 53790884 | O28: FP102 | P28: Food Product | Q28: Snack, biscuit & ready to eat | R28: 4 | S28: =INDEX('Master (Filled)'!$Z$8:$Z$37,MATCH(Q28,'Master (Filled)'!$Y$8:$Y$37,0)) -> 55000 | T28: =IF(R28>8,3%,2%) -> 0.02 | U28: =(R28*S28)-(S28*T28) -> 218900 | V28: Food Product | W28: =IF(Q28="Food Product",700,IF(Q28="Non Food Product",900,IF(Q28="General Merchandise Product",855,755))) -> 755 | X28: =SUMIF(Table1316[Category],Table1417[[#This Row],[Category]],Table1316[[Quantity ]]) -> 345 | Y28: =Table1417[[#This Row],[Inventory]]-Table1417[[#This Row],[Update ]] -> 410
A29: Net Income | B29: =B19-B26 -> 6.3893332e+08 | C29: *Income After Tax - Total Expense (1) | E29: Net Income | F29: =E17-E22 -> 2.5e+08 | G29: *Total Sales - Total Expense(2) | I29: 16 | J29: =IPMT($K8%,$I$29,$J$7,$L$13) -> -537908.84 | K29: =-PPMT($K8%,$I$29,$J$7,$L$13) -> 10545154 | L29: =L28-K29 -> 43245730 | O29: FP102 | P29: Food Product | Q29: Honey, jam, cereal and cheese | R29: 3 | S29: =INDEX('Master (Filled)'!$Z$8:$Z$37,MATCH(Q29,'Master (Filled)'!$Y$8:$Y$37,0)) -> 155000 | T29: =IF(R29>8,3%,2%) -> 0.02 | U29: =(R29*S29)-(S29*T29) -> 461900 | V29: Food Product | W29: =IF(Q29="Food Product",700,IF(Q29="Non Food Product",900,IF(Q29="General Merchandise Product",855,755))) -> 755 | X29: =SUMIF(Table1316[Category],Table1417[[#This Row],[Category]],Table1316[[Quantity ]]) -> 345 | Y29: =Table1417[[#This Row],[Inventory]]-Table1417[[#This Row],[Update ]] -> 410
I30: 17 | J30: =IPMT($K8%,$I$30,$J$7,$L$13) -> -432457.3 | K30: =-PPMT($K8%,$I$30,$J$7,$L$13) -> 10650606 | L30: =L29-K30 -> 32595124 | O30: FP102 | P30: Food Product | Q30: Snack, biscuit & ready to eat | R30: 2 | S30: =INDEX('Master (Filled)'!$Z$8:$Z$37,MATCH(Q30,'Master (Filled)'!$Y$8:$Y$37,0)) -> 55000 | T30: =IF(R30>8,3%,2%) -> 0.02 | U30: =(R30*S30)-(S30*T30) -> 108900 | V30: Food Product | W30: =IF(Q30="Food Product",700,IF(Q30="Non Food Product",900,IF(Q30="General Merchandise Product",855,755))) -> 755 | X30: =SUMIF(Table1316[Category],Table1417[[#This Row],[Category]],Table1316[[Quantity ]]) -> 345 | Y30: =Table1417[[#This Row],[Inventory]]-Table1417[[#This Row],[Update ]] -> 410
I31: 18 | J31: =IPMT($K8%,$I$31,$J$7,$L$13) -> -325951.24 | K31: =-PPMT($K8%,$I$31,$J$7,$L$13) -> 10757112 | L31: =L30-K31 -> 21838013 | O31: FP101 | P31: Food Product | Q31: Medicine | R31: 3 | S31: =INDEX('Master (Filled)'!$Z$8:$Z$37,MATCH(Q31,'Master (Filled)'!$Y$8:$Y$37,0)) -> 185000 | T31: =IF(R31>8,3%,2%) -> 0.02 | U31: =(R31*S31)-(S31*T31) -> 551300 | V31: Food Product | W31: =IF(Q31="Food Product",700,IF(Q31="Non Food Product",900,IF(Q31="General Merchandise Product",855,755))) -> 755 | X31: =SUMIF(Table1316[Category],Table1417[[#This Row],[Category]],Table1316[[Quantity ]]) -> 345 | Y31: =Table1417[[#This Row],[Inventory]]-Table1417[[#This Row],[Update ]] -> 410
I32: 19 | J32: =IPMT($K8%,$I$32,$J$7,$L$13) -> -218380.13 | K32: =-PPMT($K8%,$I$32,$J$7,$L$13) -> 10864683 | L32: =L31-K32 -> 10973330 | O32: FP101 | P32: Food Product | Q32: Cigarette & lighter | R32: 3 | S32: =INDEX('Master (Filled)'!$Z$8:$Z$37,MATCH(Q32,'Master (Filled)'!$Y$8:$Y$37,0)) -> 170000 | T32: =IF(R32>8,3%,2%) -> 0.02 | U32: =(R32*S32)-(S32*T32) -> 506600 | V32: Food Product | W32: =IF(Q32="Food Product",700,IF(Q32="Non Food Product",900,IF(Q32="General Merchandise Product",855,755))) -> 755 | X32: =SUMIF(Table1316[Category],Table1417[[#This Row],[Category]],Table1316[[Quantity ]]) -> 345 | Y32: =Table1417[[#This Row],[Inventory]]-Table1417[[#This Row],[Update ]] -> 410
A33: Price/item within formula average by category product | I33: 20 | J33: =IPMT($K8%,$I$33,$J$7,$L$13) -> -109733.3 | K33: =-PPMT($K8%,$I$33,$J$7,$L$13) -> 10973330 | L33: =L32-K33 -> 1.8626451e-08 | O33: NF103 | P33: Non Food Product | Q33: House hold | R33: 3 | S33: =INDEX('Master (Filled)'!$Z$8:$Z$37,MATCH(Q33,'Master (Filled)'!$Y$8:$Y$37,0)) -> 225000 | T33: =IF(R33>8,3%,2%) -> 0.02 | U33: =(R33*S33)-(S33*T33) -> 670500 | V33: Non Food Product | W33: =IF(Q33="Food Product",700,IF(Q33="Non Food Product",900,IF(Q33="General Merchandise Product",855,755))) -> 755 | X33: =SUMIF(Table1316[Category],Table1417[[#This Row],[Category]],Table1316[[Quantity ]]) -> 299 | Y33: =Table1417[[#This Row],[Inventory]]-Table1417[[#This Row],[Update ]] -> 456
B34: Food Product | C34: Non Food Product | D34: General Merchandise Product | E34: Perishable | O34: NF103 | P34: Non Food Product | Q34: Paper goods | R34: 2 | S34: =INDEX('Master (Filled)'!$Z$8:$Z$37,MATCH(Q34,'Master (Filled)'!$Y$8:$Y$37,0)) -> 45500 | T34: =IF(R34>8,3%,2%) -> 0.02 | U34: =(R34*S34)-(S34*T34) -> 90090 | V34: Non Food Product | W34: =IF(Q34="Food Product",700,IF(Q34="Non Food Product",900,IF(Q34="General Merchandise Product",855,755))) -> 755 | X34: =SUMIF(Table1316[Category],Table1417[[#This Row],[Category]],Table1316[[Quantity ]]) -> 299 | Y34: =Table1417[[#This Row],[Inventory]]-Table1417[[#This Row],[Update ]] -> 456
A35: Price/item | B35: 94245 | C35: 135628 | D35: 92559 | E35: 52731 | I35: *Interest = Formula (Lease Interest Expense (K8)%;POI;Periodic of Installment;Total Debit) | O35: NF101 | P35: Non Food Product | Q35: House hold | R35: 2 | S35: =INDEX('Master (Filled)'!$Z$8:$Z$37,MATCH(Q35,'Master (Filled)'!$Y$8:$Y$37,0)) -> 225000 | T35: =IF(R35>8,3%,2%) -> 0.02 | U35: =(R35*S35)-(S35*T35) -> 445500 | V35: Non Food Product | W35: =IF(Q35="Food Product",700,IF(Q35="Non Food Product",900,IF(Q35="General Merchandise Product",855,755))) -> 755 | X35: =SUMIF(Table1316[Category],Table1417[[#This Row],[Category]],Table1316[[Quantity ]]) -> 299 | Y35: =Table1417[[#This Row],[Inventory]]-Table1417[[#This Row],[Update ]] -> 456
A36: Inventory Stock | B36: 100 | C36: 150 | D36: 200 | E36: 250 | I36: *Principal = Formula (Lease Interest Expense (K8)%;POI;Periodic of Installment;Total Debit) | O36: NF102 | P36: Non Food Product | Q36: Paper goods | R36: 4 | S36: =INDEX('Master (Filled)'!$Z$8:$Z$37,MATCH(Q36,'Master (Filled)'!$Y$8:$Y$37,0)) -> 45500 | T36: =IF(R36>8,3%,2%) -> 0.02 | U36: =(R36*S36)-(S36*T36) -> 181090 | V36: Non Food Product | W36: =IF(Q36="Food Product",700,IF(Q36="Non Food Product",900,IF(Q36="General Merchandise Product",855,755))) -> 755 | X36: =SUMIF(Table1316[Category],Table1417[[#This Row],[Category]],Table1316[[Quantity ]]) -> 299 | Y36: =Table1417[[#This Row],[Inventory]]-Table1417[[#This Row],[Update ]] -> 456
A37: Total Price Per Stock | B37: =B35*B36 -> 9424500 | C37: =C35*C36 -> 20344200 | D37: =D35*D36 -> 18511800 | E37: =E35*E36 -> 13182750 | O37: PB104 | P37: Perishable | Q37: Snack & Candy | R37: 4 | S37: =INDEX('Master (Filled)'!$Z$8:$Z$37,MATCH(Q37,'Master (Filled)'!$Y$8:$Y$37,0)) -> 45555 | T37: =IF(R37>8,3%,2%) -> 0.02 | U37: =(R37*S37)-(S37*T37) -> 181308.9 | V37: Perishable | W37: =IF(Q37="Food Product",700,IF(Q37="Non Food Product",900,IF(Q37="General Merchandise Product",855,755))) -> 755 | X37: =SUMIF(Table1316[Category],Table1417[[#This Row],[Category]],Table1316[[Quantity ]]) -> 241 | Y37: =Table1417[[#This Row],[Inventory]]-Table1417[[#This Row],[Update ]] -> 514
O38: PB104 | P38: Perishable | Q38: Eggs | R38: 5 | S38: =INDEX('Master (Filled)'!$Z$8:$Z$37,MATCH(Q38,'Master (Filled)'!$Y$8:$Y$37,0)) -> 25500 | T38: =IF(R38>8,3%,2%) -> 0.02 | U38: =(R38*S38)-(S38*T38) -> 126990 | V38: Perishable | W38: =IF(Q38="Food Product",700,IF(Q38="Non Food Product",900,IF(Q38="General Merchandise Product",855,755))) -> 755 | X38: =SUMIF(Table1316[Category],Table1417[[#This Row],[Category]],Table1316[[Quantity ]]) -> 241 | Y38: =Table1417[[#This Row],[Inventory]]-Table1417[[#This Row],[Update ]] -> 514
O39: PB103 | P39: Perishable | Q39: Eggs | R39: 5 | S39: =INDEX('Master (Filled)'!$Z$8:$Z$37,MATCH(Q39,'Master (Filled)'!$Y$8:$Y$37,0)) -> 25500 | T39: =IF(R39>8,3%,2%) -> 0.02 | U39: =(R39*S39)-(S39*T39) -> 126990 | V39: Perishable | W39: =IF(Q39="Food Product",700,IF(Q39="Non Food Product",900,IF(Q39="General Merchandise Product",855,755))) -> 755 | X39: =SUMIF(Table1316[Category],Table1417[[#This Row],[Category]],Table1316[[Quantity ]]) -> 241 | Y39: =Table1417[[#This Row],[Inventory]]-Table1417[[#This Row],[Update ]] -> 514
A40: Administration Expense | B40: 500000 | C40: 930000 | D40: 1400000 | E40: 875000 | O40: PB101 | P40: Perishable | Q40: Fruit | R40: 7 | S40: =INDEX('Master (Filled)'!$Z$8:$Z$37,MATCH(Q40,'Master (Filled)'!$Y$8:$Y$37,0)) -> 89999 | T40: =IF(R40>8,3%,2%) -> 0.02 | U40: =(R40*S40)-(S40*T40) -> 628193.02 | V40: Perishable | W40: =IF(Q40="Food Product",700,IF(Q40="Non Food Product",900,IF(Q40="General Merchandise Product",855,755))) -> 755 | X40: =SUMIF(Table1316[Category],Table1417[[#This Row],[Category]],Table1316[[Quantity ]]) -> 241 | Y40: =Table1417[[#This Row],[Inventory]]-Table1417[[#This Row],[Update ]] -> 514
A41: Packaging Expense | B41: 850000 | C41: 1162500 | D41: 1600000 | E41: 1950000 | O41: PB101 | P41: Perishable | Q41: Fruit | R41: 8 | S41: =INDEX('Master (Filled)'!$Z$8:$Z$37,MATCH(Q41,'Master (Filled)'!$Y$8:$Y$37,0)) -> 89999 | T41: =IF(R41>8,3%,2%) -> 0.02 | U41: =(R41*S41)-(S41*T41) -> 718192.02 | V41: Perishable | W41: =IF(Q41="Food Product",700,IF(Q41="Non Food Product",900,IF(Q41="General Merchandise Product",855,755))) -> 755 | X41: =SUMIF(Table1316[Category],Table1417[[#This Row],[Category]],Table1316[[Quantity ]]) -> 241 | Y41: =Table1417[[#This Row],[Inventory]]-Table1417[[#This Row],[Update ]] -> 514
A42: Service Expense | B42: 350000 | C42: 675000 | D42: 2300000 | E42: 1750000 | O42: PB101 | P42: Perishable | Q42: Fruit | R42: 8 | S42: =INDEX('Master (Filled)'!$Z$8:$Z$37,MATCH(Q42,'Master (Filled)'!$Y$8:$Y$37,0)) -> 89999 | T42: =IF(R42>8,3%,2%) -> 0.02 | U42: =(R42*S42)-(S42*T42) -> 718192.02 | V42: Perishable | W42: =IF(Q42="Food Product",700,IF(Q42="Non Food Product",900,IF(Q42="General Merchandise Product",855,755))) -> 755 | X42: =SUMIF(Table1316[Category],Table1417[[#This Row],[Category]],Table1316[[Quantity ]]) -> 241 | Y42: =Table1417[[#This Row],[Inventory]]-Table1417[[#This Row],[Update ]] -> 514
A43: Total Expense | B43: =SUM(B40:B42) -> 1700000 | C43: =SUM(C40:C42) -> 2767500 | D43: =SUM(D40:D42) -> 5300000 | E43: =SUM(E40:E42) -> 4575000 | O43: PB104 | P43: Perishable | Q43: Eggs | R43: 7 | S43: =INDEX('Master (Filled)'!$Z$8:$Z$37,MATCH(Q43,'Master (Filled)'!$Y$8:$Y$37,0)) -> 25500 | T43: =IF(R43>8,3%,2%) -> 0.02 | U43: =(R43*S43)-(S43*T43) -> 177990 | V43: Perishable | W43: =IF(Q43="Food Product",700,IF(Q43="Non Food Product",900,IF(Q43="General Merchandise Product",855,755))) -> 755 | X43: =SUMIF(Table1316[Category],Table1417[[#This Row],[Category]],Table1316[[Quantity ]]) -> 241 | Y43: =Table1417[[#This Row],[Inventory]]-Table1417[[#This Row],[Update ]] -> 514
A44: Total Revenue | B44: =B37-B43 -> 7724500 | C44: =C37-C43 -> 17576700 | D44: =D37-D43 -> 13211800 | E44: =E37-E43 -> 8607750 | F44: *Total Sales - Total Expense(2) | O44: PB104 | P44: Perishable | Q44: Eggs | R44: 7 | S44: =INDEX('Master (Filled)'!$Z$8:$Z$37,MATCH(Q44,'Master (Filled)'!$Y$8:$Y$37,0)) -> 25500 | T44: =IF(R44>8,3%,2%) -> 0.02 | U44: =(R44*S44)-(S44*T44) -> 177990 | V44: Perishable | W44: =IF(Q44="Food Product",700,IF(Q44="Non Food Product",900,IF(Q44="General Merchandise Product",855,755))) -> 755 | X44: =SUMIF(Table1316[Category],Table1417[[#This Row],[Category]],Table1316[[Quantity ]]) -> 241 | Y44: =Table1417[[#This Row],[Inventory]]-Table1417[[#This Row],[Update ]] -> 514
O45: PB103 | P45: Perishable | Q45: Eggs | R45: 5 | S45: =INDEX('Master (Filled)'!$Z$8:$Z$37,MATCH(Q45,'Master (Filled)'!$Y$8:$Y$37,0)) -> 25500 | T45: =IF(R45>8,3%,2%) -> 0.02 | U45: =(R45*S45)-(S45*T45) -> 126990 | V45: Perishable | W45: =IF(Q45="Food Product",700,IF(Q45="Non Food Product",900,IF(Q45="General Merchandise Product",855,755))) -> 755 | X45: =SUMIF(Table1316[Category],Table1417[[#This Row],[Category]],Table1316[[Quantity ]]) -> 241 | Y45: =Table1417[[#This Row],[Inventory]]-Table1417[[#This Row],[Update ]] -> 514
O46: PB103 | P46: Perishable | Q46: Eggs | R46: 4 | S46: =INDEX('Master (Filled)'!$Z$8:$Z$37,MATCH(Q46,'Master (Filled)'!$Y$8:$Y$37,0)) -> 25500 | T46: =IF(R46>8,3%,2%) -> 0.02 | U46: =(R46*S46)-(S46*T46) -> 101490 | V46: Perishable | W46: =IF(Q46="Food Product",700,IF(Q46="Non Food Product",900,IF(Q46="General Merchandise Product",855,755))) -> 755 | X46: =SUMIF(Table1316[Category],Table1417[[#This Row],[Category]],Table1316[[Quantity ]]) -> 241 | Y46: =Table1417[[#This Row],[Inventory]]-Table1417[[#This Row],[Update ]] -> 514
O47: GM101 | P47: General Merchandise Product | Q47: Housewares & party need | R47: 6 | S47: =INDEX('Master (Filled)'!$Z$8:$Z$37,MATCH(Q47,'Master (Filled)'!$Y$8:$Y$37,0)) -> 110500 | T47: =IF(R47>8,3%,2%) -> 0.02 | U47: =(R47*S47)-(S47*T47) -> 660790 | V47: General Merchandise Product | W47: =IF(Q47="Food Product",700,IF(Q47="Non Food Product",900,IF(Q47="General Merchandise Product",855,755))) -> 755 | X47: =SUMIF(Table1316[Category],Table1417[[#This Row],[Category]],Table1316[[Quantity ]]) -> 215 | Y47: =Table1417[[#This Row],[Inventory]]-Table1417[[#This Row],[Update ]] -> 540
A48: Allocation Stakeholder Supermarket | O48: GM104 | P48: General Merchandise Product | Q48: Offce supplier & stationery | R48: 8 | S48: =INDEX('Master (Filled)'!$Z$8:$Z$37,MATCH(Q48,'Master (Filled)'!$Y$8:$Y$37,0)) -> 135500 | T48: =IF(R48>8,3%,2%) -> 0.02 | U48: =(R48*S48)-(S48*T48) -> 1081290 | V48: General Merchandise Product | W48: =IF(Q48="Food Product",700,IF(Q48="Non Food Product",900,IF(Q48="General Merchandise Product",855,755))) -> 755 | X48: =SUMIF(Table1316[Category],Table1417[[#This Row],[Category]],Table1316[[Quantity ]]) -> 215 | Y48: =Table1417[[#This Row],[Inventory]]-Table1417[[#This Row],[Update ]] -> 540
B49: Food Product | C49: Non Food Product | D49: General Merchandise Product | E49: Perishable | O49: FP104 | P49: Food Product | Q49: Baby milk & food | R49: 8 | S49: =INDEX('Master (Filled)'!$Z$8:$Z$37,MATCH(Q49,'Master (Filled)'!$Y$8:$Y$37,0)) -> 175000 | T49: =IF(R49>8,3%,2%) -> 0.02 | U49: =(R49*S49)-(S49*T49) -> 1396500 | V49: Food Product | W49: =IF(Q49="Food Product",700,IF(Q49="Non Food Product",900,IF(Q49="General Merchandise Product",855,755))) -> 755 | X49: =SUMIF(Table1316[Category],Table1417[[#This Row],[Category]],Table1316[[Quantity ]]) -> 345 | Y49: =Table1417[[#This Row],[Inventory]]-Table1417[[#This Row],[Update ]] -> 410
A50: Supermarket Location A | B50: 100 | C50: 155 | D50: 185 | E50: 100 | F50: 700 | O50: FP103 | P50: Food Product | Q50: Confectionary, candy & chocolate | R50: 9 | S50: =INDEX('Master (Filled)'!$Z$8:$Z$37,MATCH(Q50,'Master (Filled)'!$Y$8:$Y$37,0)) -> 65000 | T50: =IF(R50>8,3%,2%) -> 0.03 | U50: =(R50*S50)-(S50*T50) -> 583050 | V50: Food Product | W50: =IF(Q50="Food Product",700,IF(Q50="Non Food Product",900,IF(Q50="General Merchandise Product",855,755))) -> 755 | X50: =SUMIF(Table1316[Category],Table1417[[#This Row],[Category]],Table1316[[Quantity ]]) -> 345 | Y50: =Table1417[[#This Row],[Inventory]]-Table1417[[#This Row],[Update ]] -> 410
A51: Supermarket Location B | B51: 155 | C51: 165 | D51: 145 | E51: 85 | F51: 650 | O51: FP102 | P51: Food Product | Q51: Confectionary, candy & chocolate | R51: 11 | S51: =INDEX('Master (Filled)'!$Z$8:$Z$37,MATCH(Q51,'Master (Filled)'!$Y$8:$Y$37,0)) -> 65000 | T51: =IF(R51>8,3%,2%) -> 0.03 | U51: =(R51*S51)-(S51*T51) -> 713050 | V51: Food Product | W51: =IF(Q51="Food Product",700,IF(Q51="Non Food Product",900,IF(Q51="General Merchandise Product",855,755))) -> 755 | X51: =SUMIF(Table1316[Category],Table1417[[#This Row],[Category]],Table1316[[Quantity ]]) -> 345 | Y51: =Table1417[[#This Row],[Inventory]]-Table1417[[#This Row],[Update ]] -> 410
A52: Supermarket Location C | B52: 220 | C52: 170 | D52: 135 | E52: 150 | F52: 750 | O52: FP102 | P52: Food Product | Q52: Canned Food & dried meat | R52: 10 | S52: =INDEX('Master (Filled)'!$Z$8:$Z$37,MATCH(Q52,'Master (Filled)'!$Y$8:$Y$37,0)) -> 90000 | T52: =IF(R52>8,3%,2%) -> 0.03 | U52: =(R52*S52)-(S52*T52) -> 897300 | V52: Food Product | W52: =IF(Q52="Food Product",700,IF(Q52="Non Food Product",900,IF(Q52="General Merchandise Product",855,755))) -> 755 | X52: =SUMIF(Table1316[Category],Table1417[[#This Row],[Category]],Table1316[[Quantity ]]) -> 345 | Y52: =Table1417[[#This Row],[Inventory]]-Table1417[[#This Row],[Update ]] -> 410
A53: Supermarket Location D | B53: 180 | C53: 250 | D53: 145 | E53: 200 | F53: 850 | O53: FP102 | P53: Food Product | Q53: Spices, soya, sauce and ingredient | R53: 9 | S53: =INDEX('Master (Filled)'!$Z$8:$Z$37,MATCH(Q53,'Master (Filled)'!$Y$8:$Y$37,0)) -> 95000 | T53: =IF(R53>8,3%,2%) -> 0.03 | U53: =(R53*S53)-(S53*T53) -> 852150 | V53: Food Product | W53: =IF(Q53="Food Product",700,IF(Q53="Non Food Product",900,IF(Q53="General Merchandise Product",855,755))) -> 755 | X53: =SUMIF(Table1316[Category],Table1417[[#This Row],[Category]],Table1316[[Quantity ]]) -> 345 | Y53: =Table1417[[#This Row],[Inventory]]-Table1417[[#This Row],[Update ]] -> 410
B54: 700 | C54: 900 | D54: 855 | E54: 755 | O54: FP101 | P54: Food Product | Q54: Spices, soya, sauce and ingredient | R54: 5 | S54: =INDEX('Master (Filled)'!$Z$8:$Z$37,MATCH(Q54,'Master (Filled)'!$Y$8:$Y$37,0)) -> 95000 | T54: =IF(R54>8,3%,2%) -> 0.02 | U54: =(R54*S54)-(S54*T54) -> 473100 | V54: Food Product | W54: =IF(Q54="Food Product",700,IF(Q54="Non Food Product",900,IF(Q54="General Merchandise Product",855,755))) -> 755 | X54: =SUMIF(Table1316[Category],Table1417[[#This Row],[Category]],Table1316[[Quantity ]]) -> 345 | Y54: =Table1417[[#This Row],[Inventory]]-Table1417[[#This Row],[Update ]] -> 410
O55: FP101 | P55: Food Product | Q55: Spices, soya, sauce and ingredient | R55: 5 | S55: =INDEX('Master (Filled)'!$Z$8:$Z$37,MATCH(Q55,'Master (Filled)'!$Y$8:$Y$37,0)) -> 95000 | T55: =IF(R55>8,3%,2%) -> 0.02 | U55: =(R55*S55)-(S55*T55) -> 473100 | V55: Food Product | W55: =IF(Q55="Food Product",700,IF(Q55="Non Food Product",900,IF(Q55="General Merchandise Product",855,755))) -> 755 | X55: =SUMIF(Table1316[Category],Table1417[[#This Row],[Category]],Table1316[[Quantity ]]) -> 345 | Y55: =Table1417[[#This Row],[Inventory]]-Table1417[[#This Row],[Update ]] -> 410
O56: NF103 | P56: Non Food Product | Q56: Oral hygiene | R56: 3 | S56: =INDEX('Master (Filled)'!$Z$8:$Z$37,MATCH(Q56,'Master (Filled)'!$Y$8:$Y$37,0)) -> 115000 | T56: =IF(R56>8,3%,2%) -> 0.02 | U56: =(R56*S56)-(S56*T56) -> 342700 | V56: Non Food Product | W56: =IF(Q56="Food Product",700,IF(Q56="Non Food Product",900,IF(Q56="General Merchandise Product",855,755))) -> 755 | X56: =SUMIF(Table1316[Category],Table1417[[#This Row],[Category]],Table1316[[Quantity ]]) -> 299 | Y56: =Table1417[[#This Row],[Inventory]]-Table1417[[#This Row],[Update ]] -> 456
A57: Solving a problem to evaluated potential sales location A to location D | O57: NF103 | P57: Non Food Product | Q57: Oral hygiene | R57: 2 | S57: =INDEX('Master (Filled)'!$Z$8:$Z$37,MATCH(Q57,'Master (Filled)'!$Y$8:$Y$37,0)) -> 115000 | T57: =IF(R57>8,3%,2%) -> 0.02 | U57: =(R57*S57)-(S57*T57) -> 227700 | V57: Non Food Product | W57: =IF(Q57="Food Product",700,IF(Q57="Non Food Product",900,IF(Q57="General Merchandise Product",855,755))) -> 755 | X57: =SUMIF(Table1316[Category],Table1417[[#This Row],[Category]],Table1316[[Quantity ]]) -> 299 | Y57: =Table1417[[#This Row],[Inventory]]-Table1417[[#This Row],[Update ]] -> 456
O58: PB103 | P58: Perishable | Q58: Snack & Candy | R58: 2 | S58: =INDEX('Master (Filled)'!$Z$8:$Z$37,MATCH(Q58,'Master (Filled)'!$Y$8:$Y$37,0)) -> 45555 | T58: =IF(R58>8,3%,2%) -> 0.02 | U58: =(R58*S58)-(S58*T58) -> 90198.9 | V58: Perishable | W58: =IF(Q58="Food Product",700,IF(Q58="Non Food Product",900,IF(Q58="General Merchandise Product",855,755))) -> 755 | X58: =SUMIF(Table1316[Category],Table1417[[#This Row],[Category]],Table1316[[Quantity ]]) -> 241 | Y58: =Table1417[[#This Row],[Inventory]]-Table1417[[#This Row],[Update ]] -> 514
B59: Food Product | C59: Non Food Product | D59: General Merchandise Product | E59: Perishable | O59: PB102 | P59: Perishable | Q59: Snack & Candy | R59: 2 | S59: =INDEX('Master (Filled)'!$Z$8:$Z$37,MATCH(Q59,'Master (Filled)'!$Y$8:$Y$37,0)) -> 45555 | T59: =IF(R59>8,3%,2%) -> 0.02 | U59: =(R59*S59)-(S59*T59) -> 90198.9 | V59: Perishable | W59: =IF(Q59="Food Product",700,IF(Q59="Non Food Product",900,IF(Q59="General Merchandise Product",855,755))) -> 755 | X59: =SUMIF(Table1316[Category],Table1417[[#This Row],[Category]],Table1316[[Quantity ]]) -> 241 | Y59: =Table1417[[#This Row],[Inventory]]-Table1417[[#This Row],[Update ]] -> 514
A60: Supermarket Location A | B60: 0 | C60: 0 | D60: 700 | E60: 0 | F60: =SUM(B60:E60) -> 700 | G60: 700 | O60: NF104 | P60: Non Food Product | Q60: House hold | R60: 4 | S60: =INDEX('Master (Filled)'!$Z$8:$Z$37,MATCH(Q60,'Master (Filled)'!$Y$8:$Y$37,0)) -> 225000 | T60: =IF(R60>8,3%,2%) -> 0.02 | U60: =(R60*S60)-(S60*T60) -> 895500 | V60: Non Food Product | W60: =IF(Q60="Food Product",700,IF(Q60="Non Food Product",900,IF(Q60="General Merchandise Product",855,755))) -> 755 | X60: =SUMIF(Table1316[Category],Table1417[[#This Row],[Category]],Table1316[[Quantity ]]) -> 299 | Y60: =Table1417[[#This Row],[Inventory]]-Table1417[[#This Row],[Update ]] -> 456
A61: Supermarket Location B | B61: 0 | C61: 495 | D61: 155 | E61: 0 | F61: =SUM(B61:E61) -> 650 | G61: 650 | O61: NF101 | P61: Non Food Product | Q61: Baby need | R61: 5 | S61: =INDEX('Master (Filled)'!$Z$8:$Z$37,MATCH(Q61,'Master (Filled)'!$Y$8:$Y$37,0)) -> 195000 | T61: =IF(R61>8,3%,2%) -> 0.02 | U61: =(R61*S61)-(S61*T61) -> 971100 | V61: Non Food Product | W61: =IF(Q61="Food Product",700,IF(Q61="Non Food Product",900,IF(Q61="General Merchandise Product",855,755))) -> 755 | X61: =SUMIF(Table1316[Category],Table1417[[#This Row],[Category]],Table1316[[Quantity ]]) -> 299 | Y61: =Table1417[[#This Row],[Inventory]]-Table1417[[#This Row],[Update ]] -> 456
A62: Supermarket Location C | B62: 700 | C62: 0 | D62: 0 | E62: 50 | F62: =SUM(B62:E62) -> 750 | G62: 750 | O62: NF101 | P62: Non Food Product | Q62: Baby need | R62: 5 | S62: =INDEX('Master (Filled)'!$Z$8:$Z$37,MATCH(Q62,'Master (Filled)'!$Y$8:$Y$37,0)) -> 195000 | T62: =IF(R62>8,3%,2%) -> 0.02 | U62: =(R62*S62)-(S62*T62) -> 971100 | V62: Non Food Product | W62: =IF(Q62="Food Product",700,IF(Q62="Non Food Product",900,IF(Q62="General Merchandise Product",855,755))) -> 755 | X62: =SUMIF(Table1316[Category],Table1417[[#This Row],[Category]],Table1316[[Quantity ]]) -> 299 | Y62: =Table1417[[#This Row],[Inventory]]-Table1417[[#This Row],[Update ]] -> 456
A63: Supermarket Location D | B63: 0 | C63: 405 | D63: 0 | E63: 445 | F63: =SUM(B63:E63) -> 850 | G63: 850 | O63: NF102 | P63: Non Food Product | Q63: Baby need | R63: 7 | S63: =INDEX('Master (Filled)'!$Z$8:$Z$37,MATCH(Q63,'Master (Filled)'!$Y$8:$Y$37,0)) -> 195000 | T63: =IF(R63>8,3%,2%) -> 0.02 | U63: =(R63*S63)-(S63*T63) -> 1361100 | V63: Non Food Product | W63: =IF(Q63="Food Product",700,IF(Q63="Non Food Product",900,IF(Q63="General Merchandise Product",855,755))) -> 755 | X63: =SUMIF(Table1316[Category],Table1417[[#This Row],[Category]],Table1316[[Quantity ]]) -> 299 | Y63: =Table1417[[#This Row],[Inventory]]-Table1417[[#This Row],[Update ]] -> 456
B64: =SUM(B60:B63) -> 700 | C64: =SUM(C60:C63) -> 900 | D64: =SUM(D60:D63) -> 855 | E64: =SUM(E60:E63) -> 495 | O64: NF104 | P64: Non Food Product | Q64: House hold | R64: 7 | S64: =INDEX('Master (Filled)'!$Z$8:$Z$37,MATCH(Q64,'Master (Filled)'!$Y$8:$Y$37,0)) -> 225000 | T64: =IF(R64>8,3%,2%) -> 0.02 | U64: =(R64*S64)-(S64*T64) -> 1570500 | V64: Non Food Product | W64: =IF(Q64="Food Product",700,IF(Q64="Non Food Product",900,IF(Q64="General Merchandise Product",855,755))) -> 755 | X64: =SUMIF(Table1316[Category],Table1417[[#This Row],[Category]],Table1316[[Quantity ]]) -> 299 | Y64: =Table1417[[#This Row],[Inventory]]-Table1417[[#This Row],[Update ]] -> 456
B65: 700 | C65: 900 | D65: 855 | E65: 755 | O65: FP101 | P65: Food Product | Q65: Cake mix | R65: 7 | S65: =INDEX('Master (Filled)'!$Z$8:$Z$37,MATCH(Q65,'Master (Filled)'!$Y$8:$Y$37,0)) -> 125000 | T65: =IF(R65>8,3%,2%) -> 0.02 | U65: =(R65*S65)-(S65*T65) -> 872500 | V65: Food Product | W65: =IF(Q65="Food Product",700,IF(Q65="Non Food Product",900,IF(Q65="General Merchandise Product",855,755))) -> 755 | X65: =SUMIF(Table1316[Category],Table1417[[#This Row],[Category]],Table1316[[Quantity ]]) -> 345 | Y65: =Table1417[[#This Row],[Inventory]]-Table1417[[#This Row],[Update ]] -> 410
O66: FP102 | P66: Food Product | Q66: Medicine | R66: 8 | S66: =INDEX('Master (Filled)'!$Z$8:$Z$37,MATCH(Q66,'Master (Filled)'!$Y$8:$Y$37,0)) -> 185000 | T66: =IF(R66>8,3%,2%) -> 0.02 | U66: =(R66*S66)-(S66*T66) -> 1476300 | V66: Food Product | W66: =IF(Q66="Food Product",700,IF(Q66="Non Food Product",900,IF(Q66="General Merchandise Product",855,755))) -> 755 | X66: =SUMIF(Table1316[Category],Table1417[[#This Row],[Category]],Table1316[[Quantity ]]) -> 345 | Y66: =Table1417[[#This Row],[Inventory]]-Table1417[[#This Row],[Update ]] -> 410
A67: Net Sales | B67: =SUMPRODUCT(B60:E63,B50:E53) -> 585400 | O67: FP104 | P67: Food Product | Q67: Medicine | R67: 8 | S67: =INDEX('Master (Filled)'!$Z$8:$Z$37,MATCH(Q67,'Master (Filled)'!$Y$8:$Y$37,0)) -> 185000 | T67: =IF(R67>8,3%,2%) -> 0.02 | U67: =(R67*S67)-(S67*T67) -> 1476300 | V67: Food Product | W67: =IF(Q67="Food Product",700,IF(Q67="Non Food Product",900,IF(Q67="General Merchandise Product",855,755))) -> 755 | X67: =SUMIF(Table1316[Category],Table1417[[#This Row],[Category]],Table1316[[Quantity ]]) -> 345 | Y67: =Table1417[[#This Row],[Inventory]]-Table1417[[#This Row],[Update ]] -> 410
O68: GM104 | P68: General Merchandise Product | Q68: Apparel, towel and underwear | R68: 9 | S68: =INDEX('Master (Filled)'!$Z$8:$Z$37,MATCH(Q68,'Master (Filled)'!$Y$8:$Y$37,0)) -> 75000 | T68: =IF(R68>8,3%,2%) -> 0.03 | U68: =(R68*S68)-(S68*T68) -> 672750 | V68: General Merchandise Product | W68: =IF(Q68="Food Product",700,IF(Q68="Non Food Product",900,IF(Q68="General Merchandise Product",855,755))) -> 755 | X68: =SUMIF(Table1316[Category],Table1417[[#This Row],[Category]],Table1316[[Quantity ]]) -> 215 | Y68: =Table1417[[#This Row],[Inventory]]-Table1417[[#This Row],[Update ]] -> 540
O69: NF104 | P69: Non Food Product | Q69: Paper goods | R69: 12 | S69: =INDEX('Master (Filled)'!$Z$8:$Z$37,MATCH(Q69,'Master (Filled)'!$Y$8:$Y$37,0)) -> 45500 | T69: =IF(R69>8,3%,2%) -> 0.03 | U69: =(R69*S69)-(S69*T69) -> 544635 | V69: Non Food Product | W69: =IF(Q69="Food Product",700,IF(Q69="Non Food Product",900,IF(Q69="General Merchandise Product",855,755))) -> 755 | X69: =SUMIF(Table1316[Category],Table1417[[#This Row],[Category]],Table1316[[Quantity ]]) -> 299 | Y69: =Table1417[[#This Row],[Inventory]]-Table1417[[#This Row],[Update ]] -> 456
O70: NF101 | P70: Non Food Product | Q70: Personal care | R70: 11 | S70: =INDEX('Master (Filled)'!$Z$8:$Z$37,MATCH(Q70,'Master (Filled)'!$Y$8:$Y$37,0)) -> 85500 | T70: =IF(R70>8,3%,2%) -> 0.03 | U70: =(R70*S70)-(S70*T70) -> 937935 | V70: Non Food Product | W70: =IF(Q70="Food Product",700,IF(Q70="Non Food Product",900,IF(Q70="General Merchandise Product",855,755))) -> 755 | X70: =SUMIF(Table1316[Category],Table1417[[#This Row],[Category]],Table1316[[Quantity ]]) -> 299 | Y70: =Table1417[[#This Row],[Inventory]]-Table1417[[#This Row],[Update ]] -> 456
O71: NF101 | P71: Non Food Product | Q71: Paper goods | R71: 11 | S71: =INDEX('Master (Filled)'!$Z$8:$Z$37,MATCH(Q71,'Master (Filled)'!$Y$8:$Y$37,0)) -> 45500 | T71: =IF(R71>8,3%,2%) -> 0.03 | U71: =(R71*S71)-(S71*T71) -> 499135 | V71: Non Food Product | W71: =IF(Q71="Food Product",700,IF(Q71="Non Food Product",900,IF(Q71="General Merchandise Product",855,755))) -> 755 | X71: =SUMIF(Table1316[Category],Table1417[[#This Row],[Category]],Table1316[[Quantity ]]) -> 299 | Y71: =Table1417[[#This Row],[Inventory]]-Table1417[[#This Row],[Update ]] -> 456
O72: NF102 | P72: Non Food Product | Q72: Paper goods | R72: 15 | S72: =INDEX('Master (Filled)'!$Z$8:$Z$37,MATCH(Q72,'Master (Filled)'!$Y$8:$Y$37,0)) -> 45500 | T72: =IF(R72>8,3%,2%) -> 0.03 | U72: =(R72*S72)-(S72*T72) -> 681135 | V72: Non Food Product | W72: =IF(Q72="Food Product",700,IF(Q72="Non Food Product",900,IF(Q72="General Merchandise Product",855,755))) -> 755 | X72: =SUMIF(Table1316[Category],Table1417[[#This Row],[Category]],Table1316[[Quantity ]]) -> 299 | Y72: =Table1417[[#This Row],[Inventory]]-Table1417[[#This Row],[Update ]] -> 456
O73: NF104 | P73: Non Food Product | Q73: Personal care | R73: 13 | S73: =INDEX('Master (Filled)'!$Z$8:$Z$37,MATCH(Q73,'Master (Filled)'!$Y$8:$Y$37,0)) -> 85500 | T73: =IF(R73>8,3%,2%) -> 0.03 | U73: =(R73*S73)-(S73*T73) -> 1108935 | V73: Non Food Product | W73: =IF(Q73="Food Product",700,IF(Q73="Non Food Product",900,IF(Q73="General Merchandise Product",855,755))) -> 755 | X73: =SUMIF(Table1316[Category],Table1417[[#This Row],[Category]],Table1316[[Quantity ]]) -> 299 | Y73: =Table1417[[#This Row],[Inventory]]-Table1417[[#This Row],[Update ]] -> 456
O74: FP101 | P74: Food Product | Q74: Snack, biscuit & ready to eat | R74: 2 | S74: =INDEX('Master (Filled)'!$Z$8:$Z$37,MATCH(Q74,'Master (Filled)'!$Y$8:$Y$37,0)) -> 55000 | T74: =IF(R74>8,3%,2%) -> 0.02 | U74: =(R74*S74)-(S74*T74) -> 108900 | V74: Food Product | W74: =IF(Q74="Food Product",700,IF(Q74="Non Food Product",900,IF(Q74="General Merchandise Product",855,755))) -> 755 | X74: =SUMIF(Table1316[Category],Table1417[[#This Row],[Category]],Table1316[[Quantity ]]) -> 345 | Y74: =Table1417[[#This Row],[Inventory]]-Table1417[[#This Row],[Update ]] -> 410
O75: FP102 | P75: Food Product | Q75: Snack, biscuit & ready to eat | R75: 2 | S75: =INDEX('Master (Filled)'!$Z$8:$Z$37,MATCH(Q75,'Master (Filled)'!$Y$8:$Y$37,0)) -> 55000 | T75: =IF(R75>8,3%,2%) -> 0.02 | U75: =(R75*S75)-(S75*T75) -> 108900 | V75: Food Product | W75: =IF(Q75="Food Product",700,IF(Q75="Non Food Product",900,IF(Q75="General Merchandise Product",855,755))) -> 755 | X75: =SUMIF(Table1316[Category],Table1417[[#This Row],[Category]],Table1316[[Quantity ]]) -> 345 | Y75: =Table1417[[#This Row],[Inventory]]-Table1417[[#This Row],[Update ]] -> 410
O76: FP104 | P76: Food Product | Q76: Milk | R76: 2 | S76: =INDEX('Master (Filled)'!$Z$8:$Z$37,MATCH(Q76,'Master (Filled)'!$Y$8:$Y$37,0)) -> 70000 | T76: =IF(R76>8,3%,2%) -> 0.02 | U76: =(R76*S76)-(S76*T76) -> 138600 | V76: Food Product | W76: =IF(Q76="Food Product",700,IF(Q76="Non Food Product",900,IF(Q76="General Merchandise Product",855,755))) -> 755 | X76: =SUMIF(Table1316[Category],Table1417[[#This Row],[Category]],Table1316[[Quantity ]]) -> 345 | Y76: =Table1417[[#This Row],[Inventory]]-Table1417[[#This Row],[Update ]] -> 410
O77: GM104 | P77: General Merchandise Product | Q77: Apparel, towel and underwear | R77: 3 | S77: =INDEX('Master (Filled)'!$Z$8:$Z$37,MATCH(Q77,'Master (Filled)'!$Y$8:$Y$37,0)) -> 75000 | T77: =IF(R77>8,3%,2%) -> 0.02 | U77: =(R77*S77)-(S77*T77) -> 223500 | V77: General Merchandise Product | W77: =IF(Q77="Food Product",700,IF(Q77="Non Food Product",900,IF(Q77="General Merchandise Product",855,755))) -> 755 | X77: =SUMIF(Table1316[Category],Table1417[[#This Row],[Category]],Table1316[[Quantity ]]) -> 215 | Y77: =Table1417[[#This Row],[Inventory]]-Table1417[[#This Row],[Update ]] -> 540
O78: GM104 | P78: General Merchandise Product | Q78: Battery, film, electrical & lamp | R78: 4 | S78: =INDEX('Master (Filled)'!$Z$8:$Z$37,MATCH(Q78,'Master (Filled)'!$Y$8:$Y$37,0)) -> 85000 | T78: =IF(R78>8,3%,2%) -> 0.02 | U78: =(R78*S78)-(S78*T78) -> 338300 | V78: General Merchandise Product | W78: =IF(Q78="Food Product",700,IF(Q78="Non Food Product",900,IF(Q78="General Merchandise Product",855,755))) -> 755 | X78: =SUMIF(Table1316[Category],Table1417[[#This Row],[Category]],Table1316[[Quantity ]]) -> 215 | Y78: =Table1417[[#This Row],[Inventory]]-Table1417[[#This Row],[Update ]] -> 540
O79: GM103 | P79: General Merchandise Product | Q79: Apparel, towel and underwear | R79: 5 | S79: =INDEX('Master (Filled)'!$Z$8:$Z$37,MATCH(Q79,'Master (Filled)'!$Y$8:$Y$37,0)) -> 75000 | T79: =IF(R79>8,3%,2%) -> 0.02 | U79: =(R79*S79)-(S79*T79) -> 373500 | V79: General Merchandise Product | W79: =IF(Q79="Food Product",700,IF(Q79="Non Food Product",900,IF(Q79="General Merchandise Product",855,755))) -> 755 | X79: =SUMIF(Table1316[Category],Table1417[[#This Row],[Category]],Table1316[[Quantity ]]) -> 215 | Y79: =Table1417[[#This Row],[Inventory]]-Table1417[[#This Row],[Update ]] -> 540
... O88: PB102 | P88: Perishable | Q88: Chilled & frozen product | R88: 2 | S88: =INDEX('Master (Filled)'!$Z$8:$Z$37,MATCH(Q88,'Master (Filled)'!$Y$8:$Y$37,0)) -> 69999 | T88: =IF(R88>8,3%,2%) -> 0.02 | U88: =(R88*S88)-(S88*T88) -> 138598.02 | V88: Perishable | W88: =IF(Q88="Food Product",700,IF(Q88="Non Food Product",900,IF(Q88="General Merchandise Product",855,755))) -> 755 | X88: =SUMIF(Table1316[Category],Table1417[[#This Row],[Category]],Table1316[[Quantity ]]) -> 241 | Y88: =Table1417[[#This Row],[Inventory]]-Table1417[[#This Row],[Update ]] -> 514
O89: PB104 | P89: Perishable | Q89: Cake & bread | R89: 4 | S89: =INDEX('Master (Filled)'!$Z$8:$Z$37,MATCH(Q89,'Master (Filled)'!$Y$8:$Y$37,0)) -> 49999 | T89: =IF(R89>8,3%,2%) -> 0.02 | U89: =(R89*S89)-(S89*T89) -> 198996.02 | V89: Perishable | W89: =IF(Q90="Food Product",700,IF(Q90="Non Food Product",900,IF(Q90="General Merchandise Product",855,755))) -> 755 | X89: =SUMIF(Table1316[Category],Table1417[[#This Row],[Category]],Table1316[[Quantity ]]) -> 241 | Y89: =Table1417[[#This Row],[Inventory]]-Table1417[[#This Row],[Update ]] -> 514
O90: NF104 | P90: Non Food Product | Q90: Personal care | R90: 5 | S90: =INDEX('Master (Filled)'!$Z$8:$Z$37,MATCH(Q90,'Master (Filled)'!$Y$8:$Y$37,0)) -> 85500 | T90: =IF(R90>8,3%,2%) -> 0.02 | U90: =(R90*S90)-(S90*T90) -> 425790 | V90: Non Food Product | W90: =IF(Q91="Food Product",700,IF(Q91="Non Food Product",900,IF(Q91="General Merchandise Product",855,755))) -> 755 | X90: =SUMIF(Table1316[Category],Table1417[[#This Row],[Category]],Table1316[[Quantity ]]) -> 299 | Y90: =Table1417[[#This Row],[Inventory]]-Table1417[[#This Row],[Update ]] -> 456
O91: NF101 | P91: Non Food Product | Q91: Personal care | R91: 5 | S91: =INDEX('Master (Filled)'!$Z$8:$Z$37,MATCH(Q91,'Master (Filled)'!$Y$8:$Y$37,0)) -> 85500 | T91: =IF(R91>8,3%,2%) -> 0.02 | U91: =(R91*S91)-(S91*T91) -> 425790 | V91: Non Food Product | W91: =IF(Q91="Food Product",700,IF(Q91="Non Food Product",900,IF(Q91="General Merchandise Product",855,755))) -> 755 | X91: =SUMIF(Table1316[Category],Table1417[[#This Row],[Category]],Table1316[[Quantity ]]) -> 299 | Y91: =Table1417[[#This Row],[Inventory]]-Table1417[[#This Row],[Update ]] -> 456
O92: GM103 | P92: General Merchandise Product | Q92: Apparel, towel and underwear | R92: 7 | S92: =INDEX('Master (Filled)'!$Z$8:$Z$37,MATCH(Q92,'Master (Filled)'!$Y$8:$Y$37,0)) -> 75000 | T92: =IF(R92>8,3%,2%) -> 0.02 | U92: =(R92*S92)-(S92*T92) -> 523500 | V92: General Merchandise Product | W92: =IF(Q92="Food Product",700,IF(Q92="Non Food Product",900,IF(Q92="General Merchandise Product",855,755))) -> 755 | X92: =SUMIF(Table1316[Category],Table1417[[#This Row],[Category]],Table1316[[Quantity ]]) -> 215 | Y92: =Table1417[[#This Row],[Inventory]]-Table1417[[#This Row],[Update ]] -> 540
O93: PB102 | P93: Perishable | Q93: Chilled & frozen product | R93: 7 | S93: =INDEX('Master (Filled)'!$Z$8:$Z$37,MATCH(Q93,'Master (Filled)'!$Y$8:$Y$37,0)) -> 69999 | T93: =IF(R93>8,3%,2%) -> 0.02 | U93: =(R93*S93)-(S93*T93) -> 488593.02 | V93: Perishable | W93: =IF(Q93="Food Product",700,IF(Q93="Non Food Product",900,IF(Q93="General Merchandise Product",855,755))) -> 755 | X93: =SUMIF(Table1316[Category],Table1417[[#This Row],[Category]],Table1316[[Quantity ]]) -> 241 | Y93: =Table1417[[#This Row],[Inventory]]-Table1417[[#This Row],[Update ]] -> 514
O94: NF104 | P94: Non Food Product | Q94: Personal care | R94: 7 | S94: =INDEX('Master (Filled)'!$Z$8:$Z$37,MATCH(Q94,'Master (Filled)'!$Y$8:$Y$37,0)) -> 85500 | T94: =IF(R94>8,3%,2%) -> 0.02 | U94: =(R94*S94)-(S94*T94) -> 596790 | V94: Non Food Product | W94: =IF(Q94="Food Product",700,IF(Q94="Non Food Product",900,IF(Q94="General Merchandise Product",855,755))) -> 755 | X94: =SUMIF(Table1316[Category],Table1417[[#This Row],[Category]],Table1316[[Quantity ]]) -> 299 | Y94: =Table1417[[#This Row],[Inventory]]-Table1417[[#This Row],[Update ]] -> 456
O95: NF101 | P95: Non Food Product | Q95: Personal care | R95: 8 | S95: =INDEX('Master (Filled)'!$Z$8:$Z$37,MATCH(Q95,'Master (Filled)'!$Y$8:$Y$37,0)) -> 85500 | T95: =IF(R95>8,3%,2%) -> 0.02 | U95: =(R95*S95)-(S95*T95) -> 682290 | V95: Non Food Product | W95: =IF(Q95="Food Product",700,IF(Q95="Non Food Product",900,IF(Q95="General Merchandise Product",855,755))) -> 755 | X95: =SUMIF(Table1316[Category],Table1417[[#This Row],[Category]],Table1316[[Quantity ]]) -> 299 | Y95: =Table1417[[#This Row],[Inventory]]-Table1417[[#This Row],[Update ]] -> 456
O96: PB102 | P96: Perishable | Q96: Fruit | R96: 8 | S96: =INDEX('Master (Filled)'!$Z$8:$Z$37,MATCH(Q96,'Master (Filled)'!$Y$8:$Y$37,0)) -> 89999 | T96: =IF(R96>8,3%,2%) -> 0.02 | U96: =(R96*S96)-(S96*T96) -> 718192.02 | V96: Perishable | W96: =IF(Q96="Food Product",700,IF(Q96="Non Food Product",900,IF(Q96="General Merchandise Product",855,755))) -> 755 | X96: =SUMIF(Table1316[Category],Table1417[[#This Row],[Category]],Table1316[[Quantity ]]) -> 241 | Y96: =Table1417[[#This Row],[Inventory]]-Table1417[[#This Row],[Update ]] -> 514
O97: NF104 | P97: Non Food Product | Q97: Baby need | R97: 9 | S97: =INDEX('Master (Filled)'!$Z$8:$Z$37,MATCH(Q97,'Master (Filled)'!$Y$8:$Y$37,0)) -> 195000 | T97: =IF(R97>8,3%,2%) -> 0.03 | U97: =(R97*S97)-(S97*T97) -> 1749150 | V97: Non Food Product | W97: =IF(Q97="Food Product",700,IF(Q97="Non Food Product",900,IF(Q97="General Merchandise Product",855,755))) -> 755 | X97: =SUMIF(Table1316[Category],Table1417[[#This Row],[Category]],Table1316[[Quantity ]]) -> 299 | Y97: =Table1417[[#This Row],[Inventory]]-Table1417[[#This Row],[Update ]] -> 456
O98: NF101 | P98: Non Food Product | Q98: Baby need | R98: 12 | S98: =INDEX('Master (Filled)'!$Z$8:$Z$37,MATCH(Q98,'Master (Filled)'!$Y$8:$Y$37,0)) -> 195000 | T98: =IF(R98>8,3%,2%) -> 0.03 | U98: =(R98*S98)-(S98*T98) -> 2334150 | V98: Non Food Product | W98: =IF(Q98="Food Product",700,IF(Q98="Non Food Product",900,IF(Q98="General Merchandise Product",855,755))) -> 755 | X98: =SUMIF(Table1316[Category],Table1417[[#This Row],[Category]],Table1316[[Quantity ]]) -> 299 | Y98: =Table1417[[#This Row],[Inventory]]-Table1417[[#This Row],[Update ]] -> 456
O99: PB102 | P99: Perishable | Q99: Fruit | R99: 11 | S99: =INDEX('Master (Filled)'!$Z$8:$Z$37,MATCH(Q99,'Master (Filled)'!$Y$8:$Y$37,0)) -> 89999 | T99: =IF(R99>8,3%,2%) -> 0.03 | U99: =(R99*S99)-(S99*T99) -> 987289.03 | V99: Perishable | W99: =IF(Q99="Food Product",700,IF(Q99="Non Food Product",900,IF(Q99="General Merchandise Product",855,755))) -> 755 | X99: =SUMIF(Table1316[Category],Table1417[[#This Row],[Category]],Table1316[[Quantity ]]) -> 241 | Y99: =Table1417[[#This Row],[Inventory]]-Table1417[[#This Row],[Update ]] -> 514
O100: GM103 | P100: General Merchandise Product | Q100: Apparel, towel and underwear | R100: 3 | S100: =INDEX('Master (Filled)'!$Z$8:$Z$37,MATCH(Q100,'Master (Filled)'!$Y$8:$Y$37,0)) -> 75000 | T100: =IF(R100>8,3%,2%) -> 0.02 | U100: =(R100*S100)-(S100*T100) -> 223500 | V100: General Merchandise Product | W100: =IF(Q100="Food Product",700,IF(Q100="Non Food Product",900,IF(Q100="General Merchandise Product",855,755))) -> 755 | X100: =SUMIF(Table1316[Category],Table1417[[#This Row],[Category]],Table1316[[Quantity ]]) -> 215 | Y100: =Table1417[[#This Row],[Inventory]]-Table1417[[#This Row],[Update ]] -> 540
O101: PB102 | P101: Perishable | Q101: Chilled & frozen product | R101: 2 | S101: =INDEX('Master (Filled)'!$Z$8:$Z$37,MATCH(Q101,'Master (Filled)'!$Y$8:$Y$37,0)) -> 69999 | T101: =IF(R101>8,3%,2%) -> 0.02 | U101: =(R101*S101)-(S101*T101) -> 138598.02 | V101: Perishable | W101: =IF(Q101="Food Product",700,IF(Q101="Non Food Product",900,IF(Q101="General Merchandise Product",855,755))) -> 755 | X101: =SUMIF(Table1316[Category],Table1417[[#This Row],[Category]],Table1316[[Quantity ]]) -> 241 | Y101: =Table1417[[#This Row],[Inventory]]-Table1417[[#This Row],[Update ]] -> 514
O102: FP104 | P102: Food Product | Q102: Beverage | R102: 2 | S102: =INDEX('Master (Filled)'!$Z$8:$Z$37,MATCH(Q102,'Master (Filled)'!$Y$8:$Y$37,0)) -> 75000 | T102: =IF(R102>8,3%,2%) -> 0.02 | U102: =(R102*S102)-(S102*T102) -> 148500 | V102: Food Product | W102: =IF(Q102="Food Product",700,IF(Q102="Non Food Product",900,IF(Q102="General Merchandise Product",855,755))) -> 755 | X102: =SUMIF(Table1316[Category],Table1417[[#This Row],[Category]],Table1316[[Quantity ]]) -> 345 | Y102: =Table1417[[#This Row],[Inventory]]-Table1417[[#This Row],[Update ]] -> 410
... O184: NF104 | P184: Non Food Product | Q184: Personal care | R184: 8 | S184: =INDEX('Master (Filled)'!$Z$8:$Z$37,MATCH(Q184,'Master (Filled)'!$Y$8:$Y$37,0)) -> 85500 | T184: =IF(R184>8,3%,2%) -> 0.02 | U184: =(R184*S184)-(S184*T184) -> 682290 | V184: Non Food Product | W184: =IF(Q184="Food Product",700,IF(Q184="Non Food Product",900,IF(Q184="General Merchandise Product",855,755))) -> 755 | X184: =SUMIF(Table1316[Category],Table1417[[#This Row],[Category]],Table1316[[Quantity ]]) -> 299 | Y184: =Table1417[[#This Row],[Inventory]]-Table1417[[#This Row],[Update ]] -> 456
R185: =SUM(R5:R184) -> 1100 | U185: =SUM(U5:U184) -> 1.0482789e+08
U186: =AVERAGE(U5:U184) -> 582377.16
P189: Food Product | Q189: =COUNTIF(P5:P184,P14) -> 53
P190: Non Food Product | Q190: =COUNTIF(P5:P184,P10) -> 47
P191: General Merchandise Product | Q191: =COUNTIF(P5:P184,P162) -> 34
P192: Perishable | Q192: =COUNTIF(P5:P184,P5) -> 46

Sheet Income
A1: Input Date | B1: Quantity | C1: Tax | D1: Total Payment | E1: Estimated Income | F1: Fixed Cost | G1: Variable Cost
A2: 44959 | B2: 5 | C2: =IF(A2>8,3%,2%) -> 0.03 | D2: ='Master (Filled)'!O4 -> 248995.02 | E2: =(A2*B2)-(B2*C2) -> 224794.85 | F2: 8000 | G2: 11000
A3: 44959 | B3: 8 | C3: =IF(A3>8,3%,2%) -> 0.03 | D3: ='Master (Filled)'!O5 -> 558592.02 | E3: =(A3*B3)-(B3*C3) -> 359671.76 | F3: 8000 | G3: 11000
A4: 44959 | B4: 8 | C4: =IF(A4>8,3%,2%) -> 0.03 | D4: ='Master (Filled)'!O6 -> 398992.02 | E4: =(A4*B4)-(B4*C4) -> 359671.76 | F4: 8000 | G4: 11000
A5: 44959 | B5: 2 | C5: =IF(A5>8,3%,2%) -> 0.03 | D5: ='Master (Filled)'!O7 -> 50490 | E5: =(A5*B5)-(B5*C5) -> 89917.94 | F5: 8000 | G5: 11000
A6: 44959 | B6: 2 | C6: =IF(A6>8,3%,2%) -> 0.03 | D6: ='Master (Filled)'!O8 -> 386100 | E6: =(A6*B6)-(B6*C6) -> 89917.94 | F6: 8000 | G6: 11000
A7: 44959 | B7: 2 | C7: =IF(A7>8,3%,2%) -> 0.03 | D7: ='Master (Filled)'!O9 -> 169290 | E7: =(A7*B7)-(B7*C7) -> 89917.94 | F7: 8000 | G7: 11000
A8: 44959 | B8: 3 | C8: =IF(A8>8,3%,2%) -> 0.03 | D8: ='Master (Filled)'!O10 -> 254790 | E8: =(A8*B8)-(B8*C8) -> 134876.91 | F8: 8000 | G8: 11000
A9: 44960 | B9: 4 | C9: =IF(A9>8,3%,2%) -> 0.03 | D9: ='Master (Filled)'!O11 -> 776100 | E9: =(A9*B9)-(B9*C9) -> 179839.88 | F9: 8000 | G9: 11000
A10: 44960 | B10: 4 | C10: =IF(A10>8,3%,2%) -> 0.03 | D10: ='Master (Filled)'!O12 -> 776100 | E10: =(A10*B10)-(B10*C10) -> 179839.88 | F10: 8000 | G10: 11000
A11: 44960 | B11: 2 | C11: =IF(A11>8,3%,2%) -> 0.03 | D11: ='Master (Filled)'!O13 -> 168300 | E11: =(A11*B11)-(B11*C11) -> 89919.94 | F11: 8000 | G11: 11000
A12: 44960 | B12: 3 | C12: =IF(A12>8,3%,2%) -> 0.03 | D12: ='Master (Filled)'!O14 -> 253300 | E12: =(A12*B12)-(B12*C12) -> 134879.91 | F12: 8000 | G12: 11000
A13: 44960 | B13: 2 | C13: =IF(A13>8,3%,2%) -> 0.03 | D13: ='Master (Filled)'!O15 -> 168300 | E13: =(A13*B13)-(B13*C13) -> 89919.94 | F13: 8000 | G13: 11000
... A181: 44990 | B181: 8 | C181: =IF(A181>8,3%,2%) -> 0.03 | D181: ='Master (Filled)'!O183 -> 682290 | E181: =(A181*B181)-(B181*C181) -> 359919.76 | F181: 8000 | G181: 11000

Sheet Jumlah Category
A1: Product ID | B1: Jumlah
A2: FP | B2: =COUNTIF('Master (Filled)'!H4:H183,'Master (Filled)'!H13) -> 53
A3: NFP | B3: =COUNTIF('Master (Filled)'!H4:H183,'Master (Filled)'!H8) -> 47
A4: GMP | B4: =COUNTIF('Master (Filled)'!H4:H183,'Master (Filled)'!H16) -> 34
A5: Perishable | B5: =COUNTIF('Master (Filled)'!H4:H183,'Master (Filled)'!H4) -> 46

Sheet Persediaan
A1: Input Date | B1: Product ID | C1: Category | D1: Name of Product | E1: Quantity | F1: Price item | G1: Tax | H1: Total Payment | I1: Category | J1: Inventory | K1: Update | L1: Total Product
A2: 44959 | B2: PB103 | C2: Perishable | D2: Cake & bread | E2: 5 | F2: =INDEX('Master (Filled)'!$Z$8:$Z$37,MATCH(D2,'Master (Filled)'!$Y$8:$Y$37,0)) -> 49999 | G2: =IF(E2>8,3%,2%) -> 0.02 | H2: =(E2*F2)-(F2*G2) -> 248995.02 | I2: Perishable | J2: =IF(D2="Food Product",700,IF(D2="Non Food Product",900,IF(D2="General Merchandise Product",855,755))) -> 755 | K2: =SUMIF(Table1316[Category],Table14174[[#This Row],[Category]],Table1316[[Quantity ]]) -> 241 | L2: =Table14174[[#This Row],[Inventory]]-Table14174[[#This Row],[Update ]] -> 514
A3: 44959 | B3: PB101 | C3: Perishable | D3: Chilled & frozen product | E3: 8 | F3: =INDEX('Master (Filled)'!$Z$8:$Z$37,MATCH(D3,'Master (Filled)'!$Y$8:$Y$37,0)) -> 69999 | G3: =IF(E3>8,3%,2%) -> 0.02 | H3: =(E3*F3)-(F3*G3) -> 558592.02 | I3: Perishable | J3: =IF(D3="Food Product",700,IF(D3="Non Food Product",900,IF(D3="General Merchandise Product",855,755))) -> 755 | K3: =SUMIF(Table1316[Category],Table14174[[#This Row],[Category]],Table1316[[Quantity ]]) -> 241 | L3: =Table14174[[#This Row],[Inventory]]-Table14174[[#This Row],[Update ]] -> 514
A4: 44959 | B4: PB103 | C4: Perishable | D4: Cake & bread | E4: 8 | F4: =INDEX('Master (Filled)'!$Z$8:$Z$37,MATCH(D4,'Master (Filled)'!$Y$8:$Y$37,0)) -> 49999 | G4: =IF(E4>8,3%,2%) -> 0.02 | H4: =(E4*F4)-(F4*G4) -> 398992.02 | I4: Perishable | J4: =IF(D4="Food Product",700,IF(D4="Non Food Product",900,IF(D4="General Merchandise Product",855,755))) -> 755 | K4: =SUMIF(Table1316[Category],Table14174[[#This Row],[Category]],Table1316[[Quantity ]]) -> 241 | L4: =Table14174[[#This Row],[Inventory]]-Table14174[[#This Row],[Update ]] -> 514
A5: 44959 | B5: PB102 | C5: Perishable | D5: Eggs | E5: 2 | F5: =INDEX('Master (Filled)'!$Z$8:$Z$37,MATCH(D5,'Master (Filled)'!$Y$8:$Y$37,0)) -> 25500 | G5: =IF(E5>8,3%,2%) -> 0.02 | H5: =(E5*F5)-(F5*G5) -> 50490 | I5: Perishable | J5: =IF(D5="Food Product",700,IF(D5="Non Food Product",900,IF(D5="General Merchandise Product",855,755))) -> 755 | K5: =SUMIF(Table1316[Category],Table14174[[#This Row],[Category]],Table1316[[Quantity ]]) -> 241 | L5: =Table14174[[#This Row],[Inventory]]-Table14174[[#This Row],[Update ]] -> 514
A6: 44959 | B6: NF104 | C6: Non Food Product | D6: Baby need | E6: 2 | F6: =INDEX('Master (Filled)'!$Z$8:$Z$37,MATCH(D6,'Master (Filled)'!$Y$8:$Y$37,0)) -> 195000 | G6: =IF(E6>8,3%,2%) -> 0.02 | H6: =(E6*F6)-(F6*G6) -> 386100 | I6: Non Food Product | J6: =IF(D6="Food Product",700,IF(D6="Non Food Product",900,IF(D6="General Merchandise Product",855,755))) -> 755 | K6: =SUMIF(Table1316[Category],Table14174[[#This Row],[Category]],Table1316[[Quantity ]]) -> 299 | L6: =Table14174[[#This Row],[Inventory]]-Table14174[[#This Row],[Update ]] -> 456
A7: 44959 | B7: NF101 | C7: Non Food Product | D7: Personal care | E7: 2 | F7: =INDEX('Master (Filled)'!$Z$8:$Z$37,MATCH(D7,'Master (Filled)'!$Y$8:$Y$37,0)) -> 85500 | G7: =IF(E7>8,3%,2%) -> 0.02 | H7: =(E7*F7)-(F7*G7) -> 169290 | I7: Non Food Product | J7: =IF(D7="Food Product",700,IF(D7="Non Food Product",900,IF(D7="General Merchandise Product",855,755))) -> 755 | K7: =SUMIF(Table1316[Category],Table14174[[#This Row],[Category]],Table1316[[Quantity ]]) -> 299 | L7: =Table14174[[#This Row],[Inventory]]-Table14174[[#This Row],[Update ]] -> 456
A8: 44959 | B8: NF101 | C8: Non Food Product | D8: Personal care | E8: 3 | F8: =INDEX('Master (Filled)'!$Z$8:$Z$37,MATCH(D8,'Master (Filled)'!$Y$8:$Y$37,0)) -> 85500 | G8: =IF(E8>8,3%,2%) -> 0.02 | H8: =(E8*F8)-(F8*G8) -> 254790 | I8: Non Food Product | J8: =IF(D8="Food Product",700,IF(D8="Non Food Product",900,IF(D8="General Merchandise Product",855,755))) -> 755 | K8: =SUMIF(Table1316[Category],Table14174[[#This Row],[Category]],Table1316[[Quantity ]]) -> 299 | L8: =Table14174[[#This Row],[Inventory]]-Table14174[[#This Row],[Update ]] -> 456
A9: 44960 | B9: NF102 | C9: Non Food Product | D9: Baby need | E9: 4 | F9: =INDEX('Master (Filled)'!$Z$8:$Z$37,MATCH(D9,'Master (Filled)'!$Y$8:$Y$37,0)) -> 195000 | G9: =IF(E9>8,3%,2%) -> 0.02 | H9: =(E9*F9)-(F9*G9) -> 776100 | I9: Non Food Product | J9: =IF(D9="Food Product",700,IF(D9="Non Food Product",900,IF(D9="General Merchandise Product",855,755))) -> 755 | K9: =SUMIF(Table1316[Category],Table14174[[#This Row],[Category]],Table1316[[Quantity ]]) -> 299 | L9: =Table14174[[#This Row],[Inventory]]-Table14174[[#This Row],[Update ]] -> 456
A10: 44960 | B10: NF104 | C10: Non Food Product | D10: Baby need | E10: 4 | F10: =INDEX('Master (Filled)'!$Z$8:$Z$37,MATCH(D10,'Master (Filled)'!$Y$8:$Y$37,0)) -> 195000 | G10: =IF(E10>8,3%,2%) -> 0.02 | H10: =(E10*F10)-(F10*G10) -> 776100 | I10: Non Food Product | J10: =IF(D10="Food Product",700,IF(D10="Non Food Product",900,IF(D10="General Merchandise Product",855,755))) -> 755 | K10: =SUMIF(Table1316[Category],Table14174[[#This Row],[Category]],Table1316[[Quantity ]]) -> 299 | L10: =Table14174[[#This Row],[Inventory]]-Table14174[[#This Row],[Update ]] -> 456
A11: 44960 | B11: FP101 | C11: Food Product | D11: Instant Noodle & Food | E11: 2 | F11: =INDEX('Master (Filled)'!$Z$8:$Z$37,MATCH(D11,'Master (Filled)'!$Y$8:$Y$37,0)) -> 85000 | G11: =IF(E11>8,3%,2%) -> 0.02 | H11: =(E11*F11)-(F11*G11) -> 168300 | I11: Food Product | J11: =IF(D11="Food Product",700,IF(D11="Non Food Product",900,IF(D11="General Merchandise Product",855,755))) -> 755 | K11: =SUMIF(Table1316[Category],Table14174[[#This Row],[Category]],Table1316[[Quantity ]]) -> 345 | L11: =Table14174[[#This Row],[Inventory]]-Table14174[[#This Row],[Update ]] -> 410
A12: 44960 | B12: FP102 | C12: Food Product | D12: Instant Noodle & Food | E12: 3 | F12: =INDEX('Master (Filled)'!$Z$8:$Z$37,MATCH(D12,'Master (Filled)'!$Y$8:$Y$37,0)) -> 85000 | G12: =IF(E12>8,3%,2%) -> 0.02 | H12: =(E12*F12)-(F12*G12) -> 253300 | I12: Food Product | J12: =IF(D12="Food Product",700,IF(D12="Non Food Product",900,IF(D12="General Merchandise Product",855,755))) -> 755 | K12: =SUMIF(Table1316[Category],Table14174[[#This Row],[Category]],Table1316[[Quantity ]]) -> 345 | L12: =Table14174[[#This Row],[Inventory]]-Table14174[[#This Row],[Update ]] -> 410
A13: 44960 | B13: FP104 | C13: Food Product | D13: Instant Noodle & Food | E13: 2 | F13: =INDEX('Master (Filled)'!$Z$8:$Z$37,MATCH(D13,'Master (Filled)'!$Y$8:$Y$37,0)) -> 85000 | G13: =IF(E13>8,3%,2%) -> 0.02 | H13: =(E13*F13)-(F13*G13) -> 168300 | I13: Food Product | J13: =IF(D13="Food Product",700,IF(D13="Non Food Product",900,IF(D13="General Merchandise Product",855,755))) -> 755 | K13: =SUMIF(Table1316[Category],Table14174[[#This Row],[Category]],Table1316[[Quantity ]]) -> 345 | L13: =Table14174[[#This Row],[Inventory]]-Table14174[[#This Row],[Update ]] -> 410
... A85: 44969 | B85: PB102 | C85: Perishable | D85: Chilled & frozen product | E85: 2 | F85: =INDEX('Master (Filled)'!$Z$8:$Z$37,MATCH(D85,'Master (Filled)'!$Y$8:$Y$37,0)) -> 69999 | G85: =IF(E85>8,3%,2%) -> 0.02 | H85: =(E85*F85)-(F85*G85) -> 138598.02 | I85: Perishable | J85: =IF(D85="Food Product",700,IF(D85="Non Food Product",900,IF(D85="General Merchandise Product",855,755))) -> 755 | K85: =SUMIF(Table1316[Category],Table14174[[#This Row],[Category]],Table1316[[Quantity ]]) -> 241 | L85: =Table14174[[#This Row],[Inventory]]-Table14174[[#This Row],[Update ]] -> 514
A86: 44969 | B86: PB104 | C86: Perishable | D86: Cake & bread | E86: 4 | F86: =INDEX('Master (Filled)'!$Z$8:$Z$37,MATCH(D86,'Master (Filled)'!$Y$8:$Y$37,0)) -> 49999 | G86: =IF(E86>8,3%,2%) -> 0.02 | H86: =(E86*F86)-(F86*G86) -> 198996.02 | I86: Perishable | J86: =IF(D87="Food Product",700,IF(D87="Non Food Product",900,IF(D87="General Merchandise Product",855,755))) -> 755 | K86: =SUMIF(Table1316[Category],Table14174[[#This Row],[Category]],Table1316[[Quantity ]]) -> 241 | L86: =Table14174[[#This Row],[Inventory]]-Table14174[[#This Row],[Update ]] -> 514
A87: 44969 | B87: NF104 | C87: Non Food Product | D87: Personal care | E87: 5 | F87: =INDEX('Master (Filled)'!$Z$8:$Z$37,MATCH(D87,'Master (Filled)'!$Y$8:$Y$37,0)) -> 85500 | G87: =IF(E87>8,3%,2%) -> 0.02 | H87: =(E87*F87)-(F87*G87) -> 425790 | I87: Non Food Product | J87: =IF(D88="Food Product",700,IF(D88="Non Food Product",900,IF(D88="General Merchandise Product",855,755))) -> 755 | K87: =SUMIF(Table1316[Category],Table14174[[#This Row],[Category]],Table1316[[Quantity ]]) -> 299 | L87: =Table14174[[#This Row],[Inventory]]-Table14174[[#This Row],[Update ]] -> 456
A88: 44970 | B88: NF101 | C88: Non Food Product | D88: Personal care | E88: 5 | F88: =INDEX('Master (Filled)'!$Z$8:$Z$37,MATCH(D88,'Master (Filled)'!$Y$8:$Y$37,0)) -> 85500 | G88: =IF(E88>8,3%,2%) -> 0.02 | H88: =(E88*F88)-(F88*G88) -> 425790 | I88: Non Food Product | J88: =IF(D88="Food Product",700,IF(D88="Non Food Product",900,IF(D88="General Merchandise Product",855,755))) -> 755 | K88: =SUMIF(Table1316[Category],Table14174[[#This Row],[Category]],Table1316[[Quantity ]]) -> 299 | L88: =Table14174[[#This Row],[Inventory]]-Table14174[[#This Row],[Update ]] -> 456
A89: 44970 | B89: GM103 | C89: General Merchandise Product | D89: Apparel, towel and underwear | E89: 7 | F89: =INDEX('Master (Filled)'!$Z$8:$Z$37,MATCH(D89,'Master (Filled)'!$Y$8:$Y$37,0)) -> 75000 | G89: =IF(E89>8,3%,2%) -> 0.02 | H89: =(E89*F89)-(F89*G89) -> 523500 | I89: General Merchandise Product | J89: =IF(D89="Food Product",700,IF(D89="Non Food Product",900,IF(D89="General Merchandise Product",855,755))) -> 755 | K89: =SUMIF(Table1316[Category],Table14174[[#This Row],[Category]],Table1316[[Quantity ]]) -> 215 | L89: =Table14174[[#This Row],[Inventory]]-Table14174[[#This Row],[Update ]] -> 540
A90: 44970 | B90: PB102 | C90: Perishable | D90: Chilled & frozen product | E90: 7 | F90: =INDEX('Master (Filled)'!$Z$8:$Z$37,MATCH(D90,'Master (Filled)'!$Y$8:$Y$37,0)) -> 69999 | G90: =IF(E90>8,3%,2%) -> 0.02 | H90: =(E90*F90)-(F90*G90) -> 488593.02 | I90: Perishable | J90: =IF(D90="Food Product",700,IF(D90="Non Food Product",900,IF(D90="General Merchandise Product",855,755))) -> 755 | K90: =SUMIF(Table1316[Category],Table14174[[#This Row],[Category]],Table1316[[Quantity ]]) -> 241 | L90: =Table14174[[#This Row],[Inventory]]-Table14174[[#This Row],[Update ]] -> 514
A91: 44970 | B91: NF104 | C91: Non Food Product | D91: Personal care | E91: 7 | F91: =INDEX('Master (Filled)'!$Z$8:$Z$37,MATCH(D91,'Master (Filled)'!$Y$8:$Y$37,0)) -> 85500 | G91: =IF(E91>8,3%,2%) -> 0.02 | H91: =(E91*F91)-(F91*G91) -> 596790 | I91: Non Food Product | J91: =IF(D91="Food Product",700,IF(D91="Non Food Product",900,IF(D91="General Merchandise Product",855,755))) -> 755 | K91: =SUMIF(Table1316[Category],Table14174[[#This Row],[Category]],Table1316[[Quantity ]]) -> 299 | L91: =Table14174[[#This Row],[Inventory]]-Table14174[[#This Row],[Update ]] -> 456
A92: 44970 | B92: NF101 | C92: Non Food Product | D92: Personal care | E92: 8 | F92: =INDEX('Master (Filled)'!$Z$8:$Z$37,MATCH(D92,'Master (Filled)'!$Y$8:$Y$37,0)) -> 85500 | G92: =IF(E92>8,3%,2%) -> 0.02 | H92: =(E92*F92)-(F92*G92) -> 682290 | I92: Non Food Product | J92: =IF(D92="Food Product",700,IF(D92="Non Food Product",900,IF(D92="General Merchandise Product",855,755))) -> 755 | K92: =SUMIF(Table1316[Category],Table14174[[#This Row],[Category]],Table1316[[Quantity ]]) -> 299 | L92: =Table14174[[#This Row],[Inventory]]-Table14174[[#This Row],[Update ]] -> 456
A93: 44970 | B93: PB102 | C93: Perishable | D93: Fruit | E93: 8 | F93: =INDEX('Master (Filled)'!$Z$8:$Z$37,MATCH(D93,'Master (Filled)'!$Y$8:$Y$37,0)) -> 89999 | G93: =IF(E93>8,3%,2%) -> 0.02 | H93: =(E93*F93)-(F93*G93) -> 718192.02 | I93: Perishable | J93: =IF(D93="Food Product",700,IF(D93="Non Food Product",900,IF(D93="General Merchandise Product",855,755))) -> 755 | K93: =SUMIF(Table1316[Category],Table14174[[#This Row],[Category]],Table1316[[Quantity ]]) -> 241 | L93: =Table14174[[#This Row],[Inventory]]-Table14174[[#This Row],[Update ]] -> 514
A94: 44971 | B94: NF104 | C94: Non Food Product | D94: Baby need | E94: 9 | F94: =INDEX('Master (Filled)'!$Z$8:$Z$37,MATCH(D94,'Master (Filled)'!$Y$8:$Y$37,0)) -> 195000 | G94: =IF(E94>8,3%,2%) -> 0.03 | H94: =(E94*F94)-(F94*G94) -> 1749150 | I94: Non Food Product | J94: =IF(D94="Food Product",700,IF(D94="Non Food Product",900,IF(D94="General Merchandise Product",855,755))) -> 755 | K94: =SUMIF(Table1316[Category],Table14174[[#This Row],[Category]],Table1316[[Quantity ]]) -> 299 | L94: =Table14174[[#This Row],[Inventory]]-Table14174[[#This Row],[Update ]] -> 456
A95: 44971 | B95: NF101 | C95: Non Food Product | D95: Baby need | E95: 12 | F95: =INDEX('Master (Filled)'!$Z$8:$Z$37,MATCH(D95,'Master (Filled)'!$Y$8:$Y$37,0)) -> 195000 | G95: =IF(E95>8,3%,2%) -> 0.03 | H95: =(E95*F95)-(F95*G95) -> 2334150 | I95: Non Food Product | J95: =IF(D95="Food Product",700,IF(D95="Non Food Product",900,IF(D95="General Merchandise Product",855,755))) -> 755 | K95: =SUMIF(Table1316[Category],Table14174[[#This Row],[Category]],Table1316[[Quantity ]]) -> 299 | L95: =Table14174[[#This Row],[Inventory]]-Table14174[[#This Row],[Update ]] -> 456
A96: 44971 | B96: PB102 | C96: Perishable | D96: Fruit | E96: 11 | F96: =INDEX('Master (Filled)'!$Z$8:$Z$37,MATCH(D96,'Master (Filled)'!$Y$8:$Y$37,0)) -> 89999 | G96: =IF(E96>8,3%,2%) -> 0.03 | H96: =(E96*F96)-(F96*G96) -> 987289.03 | I96: Perishable | J96: =IF(D96="Food Product",700,IF(D96="Non Food Product",900,IF(D96="General Merchandise Product",855,755))) -> 755 | K96: =SUMIF(Table1316[Category],Table14174[[#This Row],[Category]],Table1316[[Quantity ]]) -> 241 | L96: =Table14174[[#This Row],[Inventory]]-Table14174[[#This Row],[Update ]] -> 514
A97: 44971 | B97: GM103 | C97: General Merchandise Product | D97: Apparel, towel and underwear | E97: 3 | F97: =INDEX('Master (Filled)'!$Z$8:$Z$37,MATCH(D97,'Master (Filled)'!$Y$8:$Y$37,0)) -> 75000 | G97: =IF(E97>8,3%,2%) -> 0.02 | H97: =(E97*F97)-(F97*G97) -> 223500 | I97: General Merchandise Product | J97: =IF(D97="Food Product",700,IF(D97="Non Food Product",900,IF(D97="General Merchandise Product",855,755))) -> 755 | K97: =SUMIF(Table1316[Category],Table14174[[#This Row],[Category]],Table1316[[Quantity ]]) -> 215 | L97: =Table14174[[#This Row],[Inventory]]-Table14174[[#This Row],[Update ]] -> 540
A98: 44971 | B98: PB102 | C98: Perishable | D98: Chilled & frozen product | E98: 2 | F98: =INDEX('Master (Filled)'!$Z$8:$Z$37,MATCH(D98,'Master (Filled)'!$Y$8:$Y$37,0)) -> 69999 | G98: =IF(E98>8,3%,2%) -> 0.02 | H98: =(E98*F98)-(F98*G98) -> 138598.02 | I98: Perishable | J98: =IF(D98="Food Product",700,IF(D98="Non Food Product",900,IF(D98="General Merchandise Product",855,755))) -> 755 | K98: =SUMIF(Table1316[Category],Table14174[[#This Row],[Category]],Table1316[[Quantity ]]) -> 241 | L98: =Table14174[[#This Row],[Inventory]]-Table14174[[#This Row],[Update ]] -> 514
A99: 44972 | B99: FP104 | C99: Food Product | D99: Beverage | E99: 2 | F99: =INDEX('Master (Filled)'!$Z$8:$Z$37,MATCH(D99,'Master (Filled)'!$Y$8:$Y$37,0)) -> 75000 | G99: =IF(E99>8,3%,2%) -> 0.02 | H99: =(E99*F99)-(F99*G99) -> 148500 | I99: Food Product | J99: =IF(D99="Food Product",700,IF(D99="Non Food Product",900,IF(D99="General Merchandise Product",855,755))) -> 755 | K99: =SUMIF(Table1316[Category],Table14174[[#This Row],[Category]],Table1316[[Quantity ]]) -> 345 | L99: =Table14174[[#This Row],[Inventory]]-Table14174[[#This Row],[Update ]] -> 410
... A181: 44990 | B181: NF104 | C181: Non Food Product | D181: Personal care | E181: 8 | F181: =INDEX('Master (Filled)'!$Z$8:$Z$37,MATCH(D181,'Master (Filled)'!$Y$8:$Y$37,0)) -> 85500 | G181: =IF(E181>8,3%,2%) -> 0.02 | H181: =(E181*F181)-(F181*G181) -> 682290 | I181: Non Food Product | J181: =IF(D181="Food Product",700,IF(D181="Non Food Product",900,IF(D181="General Merchandise Product",855,755))) -> 755 | K181: =SUMIF(Table1316[Category],Table14174[[#This Row],[Category]],Table1316[[Quantity ]]) -> 299 | L181: =Table14174[[#This Row],[Inventory]]-Table14174[[#This Row],[Update ]] -> 456
